[{"title": "\u9057\u4e16\u84b9\u846d", "artist": ["Ace\u7ec4\u5408"], "file": "Ace\u7ec4\u5408 - \u9057\u4e16\u84b9\u846d.mp3", "storage": "music1"}, {"title": "\u9752\u82b1\u5f15", "artist": ["Ace\u7ec4\u5408"], "file": "Ace\u7ec4\u5408 - \u9752\u82b1\u5f15.mp3", "storage": "music1"}, {"title": "\u5149\u8f89\u5c81\u6708", "artist": ["Beyond"], "file": "Beyond - \u5149\u8f89\u5c81\u6708.mp3", "storage": "music1"}, {"title": "\u5927\u5730", "artist": ["Beyond"], "file": "Beyond - \u5927\u5730.mp3", "storage": "music1"}, {"title": "\u6d77\u9614\u5929\u7a7a", "artist": ["Beyond"], "file": "Beyond - \u6d77\u9614\u5929\u7a7a.mp3", "storage": "music1"}, {"title": "\u771f\u7684\u7231\u4f60", "artist": ["Beyond"], "file": "Beyond - \u771f\u7684\u7231\u4f60.mp3", "storage": "music1"}, {"title": "Yesterday Once More", "artist": ["Carpenters"], "file": "Carpenters - Yesterday Once More.mp3", "storage": "music1"}, {"title": "My Heart Will Go On", "artist": ["C\u00e9line Dion"], "file": "C\u00e9line Dion - My Heart Will Go On.mp3", "storage": "music1"}, {"title": "Big Big World", "artist": ["Emilia Rydberg"], "file": "Emilia Rydberg - Big Big World.mp3", "storage": "music1"}, {"title": "\u98ce\u82b1\u96ea\u6708", "artist": ["HITA"], "file": "HITA - \u98ce\u82b1\u96ea\u6708.mp3", "storage": "music1"}, {"title": "All of Me", "artist": ["John Legend"], "file": "John Legend - All of Me.mp3", "storage": "music1"}, {"title": "Under The Stars", "artist": ["John Legend"], "file": "John Legend - Under The Stars.mp3", "storage": "music1"}, {"title": "It's Not Good-Bye", "artist": ["Laura Pausini"], "file": "Laura Pausini - It's Not Good-Bye.mp3", "storage": "music1"}, {"title": "In The End", "artist": ["LInkin Park"], "file": "LInkin Park - In The End.mp3", "storage": "music1"}, {"title": "Numb", "artist": ["Linkin Park"], "file": "Linkin Park - Numb.mp3", "storage": "music1"}, {"title": "Say You, Say Me", "artist": ["Lionel Richie"], "file": "Lionel Richie - Say You, Say Me.mp3", "storage": "music1"}, {"title": "Heal The World", "artist": ["Michael Jackson"], "file": "Michael Jackson - Heal The World.mp3", "storage": "music1"}, {"title": "Hands Of Love", "artist": ["Miley Cyrus"], "file": "Miley Cyrus - Hands Of Love.mp3", "storage": "music1"}, {"title": "Right Here Waiting", "artist": ["Richard Marx"], "file": "Richard Marx - Right Here Waiting.mp3", "storage": "music1"}, {"title": "You Raise Me Up", "artist": ["Secret Garden"], "file": "Secret Garden - You Raise Me Up.mp3", "storage": "music1"}, {"title": "The Heart Wants What It Wants", "artist": ["Selena Gomez"], "file": "Selena Gomez - The Heart Wants What It Wants.mp3", "storage": "music1"}, {"title": "\u542c\u89c1\u590f\u81f3", "artist": ["SING\u5973\u56e2"], "file": "SING\u5973\u56e2 - \u542c\u89c1\u590f\u81f3.mp3", "storage": "music1"}, {"title": "\u67d2\u6708 ", "artist": ["SING\u5973\u56e2"], "file": "SING\u5973\u56e2 - \u67d2\u6708.mp3", "storage": "music1"}, {"title": "Michael Learns To Rock", "artist": ["Take Me To Your Heart"], "file": "Take Me To Your Heart - Michael Learns To Rock.mp3", "storage": "music1"}, {"title": "Seasons In The Sun", "artist": ["Westlife"], "file": "Westlife - Seasons In The Sun.mp3", "storage": "music1"}, {"title": "I Will Always Love You", "artist": ["Whitney Houston"], "file": "Whitney Houston - I Will Always Love You.mp3", "storage": "music1"}, {"title": "See You Again", "artist": ["Wiz Khalifa&Charlie Puth"], "file": "Wiz Khalifa&Charlie Puth - See You Again.mp3", "storage": "music1"}, {"title": "\u7406\u60f3\u4e4b\u6b4c", "artist": ["\u4e95\u5bbf"], "file": "\u4e95\u5bbf - \u7406\u60f3\u4e4b\u6b4c.mp3", "storage": "music1"}, {"title": "\u51c9\u57ce", "artist": ["\u4efb\u7136"], "file": "\u4efb\u7136 - \u51c9\u57ce.mp3", "storage": "music1"}, {"title": "\u5c71\u5916\u5c0f\u697c\u591c\u542c\u96e8", "artist": ["\u4efb\u7136"], "file": "\u4efb\u7136 - \u5c71\u5916\u5c0f\u697c\u591c\u542c\u96e8.mp3", "storage": "music1"}, {"title": "\u6ca7\u6d77\u4e00\u58f0\u7b11", "artist": ["\u4efb\u8d24\u9f50"], "file": "\u4efb\u8d24\u9f50 - \u6ca7\u6d77\u4e00\u58f0\u7b11.mp3", "storage": "music1"}, {"title": "\u660e\u660e\u8bf4\u597d\u4e0d\u54ed", "artist": ["\u4f55\u66fc\u5a77"], "file": "\u4f55\u66fc\u5a77 - \u660e\u660e\u8bf4\u597d\u4e0d\u54ed.mp3", "storage": "music1"}, {"title": "\u73a9\u7b11\u8bdd", "artist": ["\u4f55\u66fc\u5a77"], "file": "\u4f55\u66fc\u5a77 - \u73a9\u7b11\u8bdd.mp3", "storage": "music1"}, {"title": "\u5fd8\u5c18\u8c37", "artist": ["\u5218\u73c2\u77e3"], "file": "\u5218\u73c2\u77e3 - \u5fd8\u5c18\u8c37.mp3", "storage": "music1"}, {"title": "\u5e78\u4f60\u4ece\u672a\u653e\u5f03", "artist": ["\u521d\u590f\u5c0f\u6eaa"], "file": "\u521d\u590f\u5c0f\u6eaa - \u5e78\u4f60\u4ece\u672a\u653e\u5f03.mp3", "storage": "music1"}, {"title": "\u5e78\u751a", "artist": ["\u521d\u590f\u5c0f\u6eaa"], "file": "\u521d\u590f\u5c0f\u6eaa - \u5e78\u751a.mp3", "storage": "music1"}, {"title": "\u4e61\u97f5", "artist": ["\u53e4\u7b5d"], "file": "\u53e4\u7b5d - \u4e61\u97f5.mp3", "storage": "music1"}, {"title": "\u5367\u864e\u85cf\u9f99", "artist": ["\u53e4\u7b5d"], "file": "\u53e4\u7b5d - \u5367\u864e\u85cf\u9f99.mp3", "storage": "music1"}, {"title": "\u5c18\u9999", "artist": ["\u53e4\u7b5d"], "file": "\u53e4\u7b5d - \u5c18\u9999.mp3", "storage": "music1"}, {"title": "\u5de5\u4eba\u8d5e", "artist": ["\u53e4\u7b5d"], "file": "\u53e4\u7b5d - \u5de5\u4eba\u8d5e.mp3", "storage": "music1"}, {"title": "\u5e7f\u9675\u6563", "artist": ["\u53e4\u7b5d"], "file": "\u53e4\u7b5d - \u5e7f\u9675\u6563.mp3", "storage": "music1"}, {"title": "\u6625\u00b7\u8bd7\u96c6", "artist": ["\u53e4\u7b5d"], "file": "\u53e4\u7b5d - \u6625\u00b7\u8bd7\u96c6.mp3", "storage": "music1"}, {"title": "\u6625\u6c5f\u82b1\u6708\u591c", "artist": ["\u53e4\u7b5d"], "file": "\u53e4\u7b5d - \u6625\u6c5f\u82b1\u6708\u591c.mp3", "storage": "music1"}, {"title": "\u6625\u8272\u5982\u8bb8", "artist": ["\u53e4\u7b5d"], "file": "\u53e4\u7b5d - \u6625\u8272\u5982\u8bb8.mp3", "storage": "music1"}, {"title": "\u6c34\u58a8\u5170\u4ead", "artist": ["\u53e4\u7b5d"], "file": "\u53e4\u7b5d - \u6c34\u58a8\u5170\u4ead.mp3", "storage": "music1"}, {"title": "\u6d63\u82b1\u8bed", "artist": ["\u53e4\u7b5d"], "file": "\u53e4\u7b5d - \u6d63\u82b1\u8bed.mp3", "storage": "music1"}, {"title": "\u7572\u5c71\u8336\u6b4c", "artist": ["\u53e4\u7b5d"], "file": "\u53e4\u7b5d - \u7572\u5c71\u8336\u6b4c.mp3", "storage": "music1"}, {"title": "\u7fe1\u7fe0\u767b\u6f6d", "artist": ["\u53e4\u7b5d"], "file": "\u53e4\u7b5d - \u7fe1\u7fe0\u767b\u6f6d.mp3", "storage": "music1"}, {"title": "\u9006\u6c34\u884c\u8239", "artist": ["\u53e4\u7b5d"], "file": "\u53e4\u7b5d - \u9006\u6c34\u884c\u8239.mp3", "storage": "music1"}, {"title": "\u94c1\u9a6c\u541f", "artist": ["\u53e4\u7b5d"], "file": "\u53e4\u7b5d - \u94c1\u9a6c\u541f.mp3", "storage": "music1"}, {"title": "\u9999\u5c71\u5c04\u9f13", "artist": ["\u53e4\u7b5d"], "file": "\u53e4\u7b5d - \u9999\u5c71\u5c04\u9f13.mp3", "storage": "music1"}, {"title": "\u4e0e\u4f60\u6700\u540e\u7684\u590f\u5929", "artist": ["\u53f8\u590f"], "file": "\u53f8\u590f - \u4e0e\u4f60\u6700\u540e\u7684\u590f\u5929.mp3", "storage": "music1"}, {"title": "\u6bcf\u56e0\u7a1a\u8da3\u6d88\u6d53\u590f", "artist": ["\u53f8\u590f"], "file": "\u53f8\u590f - \u6bcf\u56e0\u7a1a\u8da3\u6d88\u6d53\u590f.mp3", "storage": "music1"}, {"title": "\u53c8\u5e74", "artist": ["\u5929\u6642"], "file": "\u5929\u6642 - \u53c8\u5e74.mp3", "storage": "music1"}, {"title": "\u6211\u6000\u5ff5\u7684", "artist": ["\u5b59\u71d5\u59ff"], "file": "\u5b59\u71d5\u59ff - \u6211\u6000\u5ff5\u7684.mp3", "storage": "music1"}, {"title": "\u7eff\u5149", "artist": ["\u5b59\u71d5\u59ff"], "file": "\u5b59\u71d5\u59ff - \u7eff\u5149.mp3", "storage": "music1"}, {"title": "\u9047\u89c1", "artist": ["\u5b59\u71d5\u59ff"], "file": "\u5b59\u71d5\u59ff - \u9047\u89c1.mp3", "storage": "music1"}, {"title": "\u5b89\u548c\u6865", "artist": ["\u5b8b\u51ac\u91ce"], "file": "\u5b8b\u51ac\u91ce - \u5b89\u548c\u6865.mp3", "storage": "music1"}, {"title": "\u5c0f\u65f6\u5019", "artist": ["\u5c11\u53f8\u547d"], "file": "\u5c11\u53f8\u547d - \u5c0f\u65f6\u5019.mp3", "storage": "music1"}, {"title": "\u6885\u575e\u5bfb\u8336", "artist": ["\u5c11\u53f8\u547d"], "file": "\u5c11\u53f8\u547d - \u6885\u575e\u5bfb\u8336.mp3", "storage": "music1"}, {"title": "\u6c34\u58a8\u6c5f\u5357", "artist": ["\u5c11\u53f8\u547d"], "file": "\u5c11\u53f8\u547d - \u6c34\u58a8\u6c5f\u5357.mp3", "storage": "music1"}, {"title": "\u6e05\u6b4c\u6d41\u89de", "artist": ["\u5c11\u53f8\u547d"], "file": "\u5c11\u53f8\u547d - \u6e05\u6b4c\u6d41\u89de.mp3", "storage": "music1"}, {"title": "\u7476\u7434", "artist": ["\u5c11\u53f8\u547d"], "file": "\u5c11\u53f8\u547d - \u7476\u7434.mp3", "storage": "music1"}, {"title": "\u5047\u884c\u50e7", "artist": ["\u5d14\u5065"], "file": "\u5d14\u5065 - \u5047\u884c\u50e7.mp3", "storage": "music1"}, {"title": "\u4e0b\u4e00\u7ad9\uff0c\u8336\u5c71\u5218", "artist": ["\u623f\u4e1c\u7684\u732b"], "file": "\u623f\u4e1c\u7684\u732b - \u4e0b\u4e00\u7ad9\uff0c\u8336\u5c71\u5218.mp3", "storage": "music1"}, {"title": "\u5356\u4e2a\u840c", "artist": ["\u672c\u516e"], "file": "\u672c\u516e - \u5356\u4e2a\u840c.mp3", "storage": "music1"}, {"title": "\u60c5\u4eba\u8282\u7684\u591c\u665a", "artist": ["\u672c\u516e"], "file": "\u672c\u516e - \u60c5\u4eba\u8282\u7684\u591c\u665a.mp3", "storage": "music1"}, {"title": "\u60c5\u6b4c\u60a0\u626c", "artist": ["\u672c\u516e"], "file": "\u672c\u516e - \u60c5\u6b4c\u60a0\u626c.mp3", "storage": "music1"}, {"title": "\u60c5\u82b1", "artist": ["\u672c\u516e"], "file": "\u672c\u516e - \u60c5\u82b1.mp3", "storage": "music1"}, {"title": "\u6218\u653e", "artist": ["\u672c\u516e"], "file": "\u672c\u516e - \u6218\u653e.mp3", "storage": "music1"}, {"title": "\u672a\u6210\u5e74", "artist": ["\u672c\u516e"], "file": "\u672c\u516e - \u672a\u6210\u5e74.mp3", "storage": "music1"}, {"title": "\u751c\u871c Full in love", "artist": ["\u672c\u516e"], "file": "\u672c\u516e - \u751c\u871c Full in love.mp3", "storage": "music1"}, {"title": "\u5e73\u51e1\u4e4b\u8def", "artist": ["\u6734\u6811"], "file": "\u6734\u6811 - \u5e73\u51e1\u4e4b\u8def.mp3", "storage": "music1"}, {"title": "\u7ea2\u65e5", "artist": ["\u674e\u514b\u52e4"], "file": "\u674e\u514b\u52e4 - \u7ea2\u65e5.mp3", "storage": "music1"}, {"title": "Always Online", "artist": ["\u6797\u4fca\u6770"], "file": "\u6797\u4fca\u6770 - Always Online.mp3", "storage": "music1"}, {"title": "Baby Baby", "artist": ["\u6797\u4fca\u6770"], "file": "\u6797\u4fca\u6770 - Baby Baby.mp3", "storage": "music1"}, {"title": "Cinderella", "artist": ["\u6797\u4fca\u6770"], "file": "\u6797\u4fca\u6770 - Cinderella.mp3", "storage": "music1"}, {"title": "Cries In A Distance", "artist": ["\u6797\u4fca\u6770"], "file": "\u6797\u4fca\u6770 - Cries In A Distance.mp3", "storage": "music1"}, {"title": "Endless Road", "artist": ["\u6797\u4fca\u6770"], "file": "\u6797\u4fca\u6770 - Endless Road.mp3", "storage": "music1"}, {"title": "K-O", "artist": ["\u6797\u4fca\u6770"], "file": "\u6797\u4fca\u6770 - K-O.mp3", "storage": "music1"}, {"title": "Lier and Accuser", "artist": ["\u6797\u4fca\u6770"], "file": "\u6797\u4fca\u6770 - Lier and Accuser.mp3", "storage": "music1"}, {"title": "Love U U", "artist": ["\u6797\u4fca\u6770"], "file": "\u6797\u4fca\u6770 - Love U U.mp3", "storage": "music1"}, {"title": "Now That She's Gone", "artist": ["\u6797\u4fca\u6770"], "file": "\u6797\u4fca\u6770 - Now That She's Gone.mp3", "storage": "music1"}, {"title": "One Shot\uff08\u738b\u529b\u5b8f\u5c0f\u63d0\u7434\u7279\u522b\u6f14\u594f\uff09", "artist": ["\u6797\u4fca\u6770"], "file": "\u6797\u4fca\u6770 - One Shot\uff08\u738b\u529b\u5b8f\u5c0f\u63d0\u7434\u7279\u522b\u6f14\u594f\uff09.mp3", "storage": "music1"}, {"title": "Sixology", "artist": ["\u6797\u4fca\u6770"], "file": "\u6797\u4fca\u6770 - Sixology.mp3", "storage": "music1"}, {"title": "Still Moving Under Gunfire", "artist": ["\u6797\u4fca\u6770"], "file": "\u6797\u4fca\u6770 - Still Moving Under Gunfire.mp3", "storage": "music1"}, {"title": "Too Bad", "artist": ["\u6797\u4fca\u6770"], "file": "\u6797\u4fca\u6770 - Too Bad.mp3", "storage": "music1"}, {"title": "Until The Day", "artist": ["\u6797\u4fca\u6770"], "file": "\u6797\u4fca\u6770 - Until The Day.mp3", "storage": "music1"}, {"title": "We Together", "artist": ["\u6797\u4fca\u6770"], "file": "\u6797\u4fca\u6770 - We Together.mp3", "storage": "music1"}, {"title": "X", "artist": ["\u6797\u4fca\u6770"], "file": "\u6797\u4fca\u6770 - X.mp3", "storage": "music1"}, {"title": "\u4e00\u4e2a\u53c8\u4e00\u4e2a", "artist": ["\u6797\u4fca\u6770"], "file": "\u6797\u4fca\u6770 - \u4e00\u4e2a\u53c8\u4e00\u4e2a.mp3", "storage": "music1"}, {"title": "\u4e00\u5343\u5e74\u4ee5\u524d", "artist": ["\u6797\u4fca\u6770"], "file": "\u6797\u4fca\u6770 - \u4e00\u5343\u5e74\u4ee5\u524d.mp3", "storage": "music1"}, {"title": "\u4e00\u5343\u5e74\u4ee5\u540e", "artist": ["\u6797\u4fca\u6770"], "file": "\u6797\u4fca\u6770 - \u4e00\u5343\u5e74\u4ee5\u540e.mp3", "storage": "music1"}, {"title": "\u4e00\u5343\u5e74\u540e\u8bb0\u5f97\u6211(\u9690\u85cf\u66f2\u76ee)", "artist": ["\u6797\u4fca\u6770"], "file": "\u6797\u4fca\u6770 - \u4e00\u5343\u5e74\u540e\u8bb0\u5f97\u6211(\u9690\u85cf\u66f2\u76ee).mp3", "storage": "music1"}, {"title": "\u4e00\u5f00\u59cb\u2026", "artist": ["\u6797\u4fca\u6770"], "file": "\u6797\u4fca\u6770 - \u4e00\u5f00\u59cb\u2026.mp3", "storage": "music1"}, {"title": "\u4e00\u751f\u7684\u7231", "artist": ["\u6797\u4fca\u6770"], "file": "\u6797\u4fca\u6770 - \u4e00\u751f\u7684\u7231.mp3", "storage": "music1"}, {"title": "\u4e00\u773c\u4e07\u5e74", "artist": ["\u6797\u4fca\u6770"], "file": "\u6797\u4fca\u6770 - \u4e00\u773c\u4e07\u5e74.mp3", "storage": "music1"}, {"title": "\u4e0d\u4e3a\u8c01\u800c\u4f5c\u7684\u6b4c", "artist": ["\u6797\u4fca\u6770"], "file": "\u6797\u4fca\u6770 - \u4e0d\u4e3a\u8c01\u800c\u4f5c\u7684\u6b4c.mp3", "storage": "music1"}, {"title": "\u4e0d\u5b58\u5728\u7684\u60c5\u4eba", "artist": ["\u6797\u4fca\u6770"], "file": "\u6797\u4fca\u6770 - \u4e0d\u5b58\u5728\u7684\u60c5\u4eba.mp3", "storage": "music1"}, {"title": "\u4e0d\u61c2", "artist": ["\u6797\u4fca\u6770"], "file": "\u6797\u4fca\u6770 - \u4e0d\u61c2.mp3", "storage": "music1"}, {"title": "\u4e0d\u6b7b\u4e4b\u8eab", "artist": ["\u6797\u4fca\u6770"], "file": "\u6797\u4fca\u6770 - \u4e0d\u6b7b\u4e4b\u8eab.mp3", "storage": "music1"}, {"title": "\u4e0d\u6d41\u6cea\u7684\u673a\u573a", "artist": ["\u6797\u4fca\u6770"], "file": "\u6797\u4fca\u6770 - \u4e0d\u6d41\u6cea\u7684\u673a\u573a.mp3", "storage": "music1"}, {"title": "\u4e0d\u6f6e\u4e0d\u7528\u82b1\u94b1", "artist": ["\u6797\u4fca\u6770"], "file": "\u6797\u4fca\u6770 - \u4e0d\u6f6e\u4e0d\u7528\u82b1\u94b1.mp3", "storage": "music1"}, {"title": "\u4ee5\u540e\u8981\u505a\u7684\u4e8b", "artist": ["\u6797\u4fca\u6770"], "file": "\u6797\u4fca\u6770 - \u4ee5\u540e\u8981\u505a\u7684\u4e8b.mp3", "storage": "music1"}, {"title": "\u4f1a\u6709\u90a3\u4e48\u4e00\u5929", "artist": ["\u6797\u4fca\u6770"], "file": "\u6797\u4fca\u6770 - \u4f1a\u6709\u90a3\u4e48\u4e00\u5929.mp3", "storage": "music1"}, {"title": "\u4f1a\u8bfb\u4e66", "artist": ["\u6797\u4fca\u6770"], "file": "\u6797\u4fca\u6770 - \u4f1a\u8bfb\u4e66.mp3", "storage": "music1"}, {"title": "\u4f1f\u5927\u7684\u6e3a\u5c0f", "artist": ["\u6797\u4fca\u6770"], "file": "\u6797\u4fca\u6770 - \u4f1f\u5927\u7684\u6e3a\u5c0f.mp3", "storage": "music1"}, {"title": "\u4f60\u8981\u7684\u4e0d\u662f\u6211", "artist": ["\u6797\u4fca\u6770"], "file": "\u6797\u4fca\u6770 - \u4f60\u8981\u7684\u4e0d\u662f\u6211.mp3", "storage": "music1"}, {"title": "\u4f60\uff0c\u6709\u6ca1\u6709\u8fc7", "artist": ["\u6797\u4fca\u6770"], "file": "\u6797\u4fca\u6770 - \u4f60\uff0c\u6709\u6ca1\u6709\u8fc7.mp3", "storage": "music1"}, {"title": "\u4f60\uff0c\u6709\u6ca1\u6709\u8fc7\uff08Livehouse\u7248\uff09", "artist": ["\u6797\u4fca\u6770"], "file": "\u6797\u4fca\u6770 - \u4f60\uff0c\u6709\u6ca1\u6709\u8fc7\uff08Livehouse\u7248\uff09.mp3", "storage": "music1"}, {"title": "\u4fee\u70bc\u7231\u60c5", "artist": ["\u6797\u4fca\u6770"], "file": "\u6797\u4fca\u6770 - \u4fee\u70bc\u7231\u60c5.mp3", "storage": "music1"}, {"title": "\u5173\u952e\u8bcd", "artist": ["\u6797\u4fca\u6770"], "file": "\u6797\u4fca\u6770 - \u5173\u952e\u8bcd.mp3", "storage": "music1"}, {"title": "\u51bb\u7ed3", "artist": ["\u6797\u4fca\u6770"], "file": "\u6797\u4fca\u6770 - \u51bb\u7ed3.mp3", "storage": "music1"}, {"title": "\u526a\u4e91\u8005", "artist": ["\u6797\u4fca\u6770"], "file": "\u6797\u4fca\u6770 - \u526a\u4e91\u8005.mp3", "storage": "music1"}, {"title": "\u5341\u79d2\u7684\u6c96\u52a8", "artist": ["\u6797\u4fca\u6770"], "file": "\u6797\u4fca\u6770 - \u5341\u79d2\u7684\u6c96\u52a8.mp3", "storage": "music1"}, {"title": "\u538b\u529b", "artist": ["\u6797\u4fca\u6770"], "file": "\u6797\u4fca\u6770 - \u538b\u529b.mp3", "storage": "music1"}, {"title": "\u539f\u6765", "artist": ["\u6797\u4fca\u6770"], "file": "\u6797\u4fca\u6770 - \u539f\u6765.mp3", "storage": "music1"}, {"title": "\u53ea\u5bf9\u4f60\u6709\u611f\u89c9", "artist": ["\u6797\u4fca\u6770"], "file": "\u6797\u4fca\u6770 - \u53ea\u5bf9\u4f60\u6709\u611f\u89c9.mp3", "storage": "music1"}, {"title": "\u53ea\u8981\u6709\u4f60\u7684\u5730\u65b9(\u665a\u5b89\u7248)", "artist": ["\u6797\u4fca\u6770"], "file": "\u6797\u4fca\u6770 - \u53ea\u8981\u6709\u4f60\u7684\u5730\u65b9(\u665a\u5b89\u7248).mp3", "storage": "music1"}, {"title": "\u53ea\u8981\u6709\u4f60\u7684\u5730\u65b9", "artist": ["\u6797\u4fca\u6770"], "file": "\u6797\u4fca\u6770 - \u53ea\u8981\u6709\u4f60\u7684\u5730\u65b9.mp3", "storage": "music1"}, {"title": "\u53ef\u60dc\u6ca1\u5982\u679c", "artist": ["\u6797\u4fca\u6770"], "file": "\u6797\u4fca\u6770 - \u53ef\u60dc\u6ca1\u5982\u679c.mp3", "storage": "music1"}, {"title": "\u542c\u4e0d\u61c2 \u6ca1\u5173\u7cfb", "artist": ["\u6797\u4fca\u6770"], "file": "\u6797\u4fca\u6770 - \u542c\u4e0d\u61c2 \u6ca1\u5173\u7cfb.mp3", "storage": "music1"}, {"title": "\u56db\u70b9\u56db\u5341\u56db", "artist": ["\u6797\u4fca\u6770"], "file": "\u6797\u4fca\u6770 - \u56db\u70b9\u56db\u5341\u56db.mp3", "storage": "music1"}, {"title": "\u56de", "artist": ["\u6797\u4fca\u6770"], "file": "\u6797\u4fca\u6770 - \u56de.mp3", "storage": "music1"}, {"title": "\u56e0\u4f60\u800c\u5728", "artist": ["\u6797\u4fca\u6770"], "file": "\u6797\u4fca\u6770 - \u56e0\u4f60\u800c\u5728.mp3", "storage": "music1"}, {"title": "\u5723\u6240", "artist": ["\u6797\u4fca\u6770"], "file": "\u6797\u4fca\u6770 - \u5723\u6240.mp3", "storage": "music1"}, {"title": "\u5927\u7537\u4eba\u00b7\u5c0f\u5973\u5b69", "artist": ["\u6797\u4fca\u6770"], "file": "\u6797\u4fca\u6770 - \u5927\u7537\u4eba\u00b7\u5c0f\u5973\u5b69.mp3", "storage": "music1"}, {"title": "\u5929\u4f7f\u5fc3", "artist": ["\u6797\u4fca\u6770"], "file": "\u6797\u4fca\u6770 - \u5929\u4f7f\u5fc3.mp3", "storage": "music1"}, {"title": "\u5973\u513f\u5bb6", "artist": ["\u6797\u4fca\u6770"], "file": "\u6797\u4fca\u6770 - \u5973\u513f\u5bb6.mp3", "storage": "music1"}, {"title": "\u5979\u8bf4", "artist": ["\u6797\u4fca\u6770"], "file": "\u6797\u4fca\u6770 - \u5979\u8bf4.mp3", "storage": "music1"}, {"title": "\u5988\u5988\u7684\u5a1c\u9c81\u5a03", "artist": ["\u6797\u4fca\u6770"], "file": "\u6797\u4fca\u6770 - \u5988\u5988\u7684\u5a1c\u9c81\u5a03.mp3", "storage": "music1"}, {"title": "\u5b50\u5f39\u5217\u8f66", "artist": ["\u6797\u4fca\u6770"], "file": "\u6797\u4fca\u6770 - \u5b50\u5f39\u5217\u8f66.mp3", "storage": "music1"}, {"title": "\u5b66\u4e0d\u4f1a", "artist": ["\u6797\u4fca\u6770"], "file": "\u6797\u4fca\u6770 - \u5b66\u4e0d\u4f1a.mp3", "storage": "music1"}, {"title": "\u5bb3\u6015", "artist": ["\u6797\u4fca\u6770"], "file": "\u6797\u4fca\u6770 - \u5bb3\u6015.mp3", "storage": "music1"}, {"title": "\u5c0f\u74f6\u5b50-(\u7535\u5f71\u300a\u5047\u5982\u738b\u5b50\u7761\u7740\u4e86\u300b\u5370\u8c61\u66f2)", "artist": ["\u6797\u4fca\u6770"], "file": "\u6797\u4fca\u6770 - \u5c0f\u74f6\u5b50-(\u7535\u5f71\u300a\u5047\u5982\u738b\u5b50\u7761\u7740\u4e86\u300b\u5370\u8c61\u66f2).mp3", "storage": "music1"}, {"title": "\u5c31\u662f\u6211", "artist": ["\u6797\u4fca\u6770"], "file": "\u6797\u4fca\u6770 - \u5c31\u662f\u6211.mp3", "storage": "music1"}, {"title": "\u5df4\u6d1b\u514b\u5148\u751f\uff08\u738b\u529b\u5b8f\u5c0f\u63d0\u7434\u7279\u522b\u6f14\u594f\uff09", "artist": ["\u6797\u4fca\u6770"], "file": "\u6797\u4fca\u6770 - \u5df4\u6d1b\u514b\u5148\u751f\uff08\u738b\u529b\u5b8f\u5c0f\u63d0\u7434\u7279\u522b\u6f14\u594f\uff09.mp3", "storage": "music1"}, {"title": "\u5e8f\u66f2\uff1a12\u5e74\u524d", "artist": ["\u6797\u4fca\u6770"], "file": "\u6797\u4fca\u6770 - \u5e8f\u66f2\uff1a12\u5e74\u524d.mp3", "storage": "music1"}, {"title": "\u5e8f\u66f2\uff1aWelcome To The Livehouse", "artist": ["\u6797\u4fca\u6770"], "file": "\u6797\u4fca\u6770 - \u5e8f\u66f2\uff1aWelcome To The Livehouse.mp3", "storage": "music1"}, {"title": "\u5e8f\uff1a\u66d9\u5149", "artist": ["\u6797\u4fca\u6770"], "file": "\u6797\u4fca\u6770 - \u5e8f\uff1a\u66d9\u5149.mp3", "storage": "music1"}, {"title": "\u5f39\u5531", "artist": ["\u6797\u4fca\u6770"], "file": "\u6797\u4fca\u6770 - \u5f39\u5531.mp3", "storage": "music1"}, {"title": "\u5f53\u4f60", "artist": ["\u6797\u4fca\u6770"], "file": "\u6797\u4fca\u6770 - \u5f53\u4f60.mp3", "storage": "music1"}, {"title": "\u5fc3\u58bb", "artist": ["\u6797\u4fca\u6770"], "file": "\u6797\u4fca\u6770 - \u5fc3\u58bb.mp3", "storage": "music1"}, {"title": "\u6211\u5f88\u60f3\u7231\u4ed6", "artist": ["\u6797\u4fca\u6770"], "file": "\u6797\u4fca\u6770 - \u6211\u5f88\u60f3\u7231\u4ed6.mp3", "storage": "music1"}, {"title": "\u6211\u7ee7\u7eed", "artist": ["\u6797\u4fca\u6770"], "file": "\u6797\u4fca\u6770 - \u6211\u7ee7\u7eed.mp3", "storage": "music1"}, {"title": "\u6211\u8fd8\u60f3\u5979", "artist": ["\u6797\u4fca\u6770"], "file": "\u6797\u4fca\u6770 - \u6211\u8fd8\u60f3\u5979.mp3", "storage": "music1"}, {"title": "\u63e1\u4e0d\u4f4f\u7684\u4ed6", "artist": ["\u6797\u4fca\u6770"], "file": "\u6797\u4fca\u6770 - \u63e1\u4e0d\u4f4f\u7684\u4ed6.mp3", "storage": "music1"}, {"title": "\u6545\u4e8b\u7ec6\u817b", "artist": ["\u6797\u4fca\u6770"], "file": "\u6797\u4fca\u6770 - \u6545\u4e8b\u7ec6\u817b.mp3", "storage": "music1"}, {"title": "\u65b0\u5730\u7403", "artist": ["\u6797\u4fca\u6770"], "file": "\u6797\u4fca\u6770 - \u65b0\u5730\u7403.mp3", "storage": "music1"}, {"title": "\u65e0\u5c3d\u7684\u601d\u5ff5", "artist": ["\u6797\u4fca\u6770"], "file": "\u6797\u4fca\u6770 - \u65e0\u5c3d\u7684\u601d\u5ff5.mp3", "storage": "music1"}, {"title": "\u65e0\u6cd5\u514b\u5236", "artist": ["\u6797\u4fca\u6770"], "file": "\u6797\u4fca\u6770 - \u65e0\u6cd5\u514b\u5236.mp3", "storage": "music1"}, {"title": "\u65e0\u804a", "artist": ["\u6797\u4fca\u6770"], "file": "\u6797\u4fca\u6770 - \u65e0\u804a.mp3", "storage": "music1"}, {"title": "\u660e\u5929", "artist": ["\u6797\u4fca\u6770"], "file": "\u6797\u4fca\u6770 - \u660e\u5929.mp3", "storage": "music1"}, {"title": "\u661f\u7403", "artist": ["\u6797\u4fca\u6770"], "file": "\u6797\u4fca\u6770 - \u661f\u7403.mp3", "storage": "music1"}, {"title": "\u661f\u7a7a\u4e0b\u7684\u543b", "artist": ["\u6797\u4fca\u6770"], "file": "\u6797\u4fca\u6770 - \u661f\u7a7a\u4e0b\u7684\u543b.mp3", "storage": "music1"}, {"title": "\u66f9\u64cd", "artist": ["\u6797\u4fca\u6770"], "file": "\u6797\u4fca\u6770 - \u66f9\u64cd.mp3", "storage": "music1"}, {"title": "\u6728\u4e43\u4f0a", "artist": ["\u6797\u4fca\u6770"], "file": "\u6797\u4fca\u6770 - \u6728\u4e43\u4f0a.mp3", "storage": "music1"}, {"title": "\u672a\u5b8c\u6210", "artist": ["\u6797\u4fca\u6770"], "file": "\u6797\u4fca\u6770 - \u672a\u5b8c\u6210.mp3", "storage": "music1"}, {"title": "\u6740\u624b", "artist": ["\u6797\u4fca\u6770"], "file": "\u6797\u4fca\u6770 - \u6740\u624b.mp3", "storage": "music1"}, {"title": "\u6740\u624b@\u7eed", "artist": ["\u6797\u4fca\u6770"], "file": "\u6797\u4fca\u6770 - \u6740\u624b@\u7eed.mp3", "storage": "music1"}, {"title": "\u6765\u4e0d\u53ca\u4e86", "artist": ["\u6797\u4fca\u6770"], "file": "\u6797\u4fca\u6770 - \u6765\u4e0d\u53ca\u4e86.mp3", "storage": "music1"}, {"title": "\u68ee\u6797\u6d74", "artist": ["\u6797\u4fca\u6770"], "file": "\u6797\u4fca\u6770 - \u68ee\u6797\u6d74.mp3", "storage": "music1"}, {"title": "\u6c34\u4ed9", "artist": ["\u6797\u4fca\u6770"], "file": "\u6797\u4fca\u6770 - \u6c34\u4ed9.mp3", "storage": "music1"}, {"title": "\u6c5f\u5357", "artist": ["\u6797\u4fca\u6770"], "file": "\u6797\u4fca\u6770 - \u6c5f\u5357.mp3", "storage": "music1"}, {"title": "\u6c5f\u5357\uff08\u7ca4\u8bed\u7248\uff09", "artist": ["\u6797\u4fca\u6770"], "file": "\u6797\u4fca\u6770 - \u6c5f\u5357\uff08\u7ca4\u8bed\u7248\uff09.mp3", "storage": "music1"}, {"title": "\u6ce2\u95f4\u5e26", "artist": ["\u6797\u4fca\u6770"], "file": "\u6797\u4fca\u6770 - \u6ce2\u95f4\u5e26.mp3", "storage": "music1"}, {"title": "\u6d6a\u6f2b\u8840\u6db2", "artist": ["\u6797\u4fca\u6770"], "file": "\u6797\u4fca\u6770 - \u6d6a\u6f2b\u8840\u6db2.mp3", "storage": "music1"}, {"title": "\u7075\u9b42\u7684\u5171\u9e23", "artist": ["\u6797\u4fca\u6770"], "file": "\u6797\u4fca\u6770 - \u7075\u9b42\u7684\u5171\u9e23.mp3", "storage": "music1"}, {"title": "\u70b9\u4e00\u628a\u706b\u70ac", "artist": ["\u6797\u4fca\u6770"], "file": "\u6797\u4fca\u6770 - \u70b9\u4e00\u628a\u706b\u70ac.mp3", "storage": "music1"}, {"title": "\u719f\u80fd\u751f\u5de7", "artist": ["\u6797\u4fca\u6770"], "file": "\u6797\u4fca\u6770 - \u719f\u80fd\u751f\u5de7.mp3", "storage": "music1"}, {"title": "\u7231\u4e0d\u4f1a\u7edd\u8ff9", "artist": ["\u6797\u4fca\u6770"], "file": "\u6797\u4fca\u6770 - \u7231\u4e0d\u4f1a\u7edd\u8ff9.mp3", "storage": "music1"}, {"title": "\u7231\u60c5yogurt", "artist": ["\u6797\u4fca\u6770"], "file": "\u6797\u4fca\u6770 - \u7231\u60c5yogurt.mp3", "storage": "music1"}, {"title": "\u7231\u7684\u9f13\u52b1", "artist": ["\u6797\u4fca\u6770"], "file": "\u6797\u4fca\u6770 - \u7231\u7684\u9f13\u52b1.mp3", "storage": "music1"}, {"title": "\u7231\u7b11\u7684\u773c\u775b", "artist": ["\u6797\u4fca\u6770"], "file": "\u6797\u4fca\u6770 - \u7231\u7b11\u7684\u773c\u775b.mp3", "storage": "music1"}, {"title": "\u72ec\u594f", "artist": ["\u6797\u4fca\u6770"], "file": "\u6797\u4fca\u6770 - \u72ec\u594f.mp3", "storage": "music1"}, {"title": "\u72ec\u767d", "artist": ["\u6797\u4fca\u6770"], "file": "\u6797\u4fca\u6770 - \u72ec\u767d.mp3", "storage": "music1"}, {"title": "\u72ec\u821e", "artist": ["\u6797\u4fca\u6770"], "file": "\u6797\u4fca\u6770 - \u72ec\u821e.mp3", "storage": "music1"}, {"title": "\u751f\u751f", "artist": ["\u6797\u4fca\u6770"], "file": "\u6797\u4fca\u6770 - \u751f\u751f.mp3", "storage": "music1"}, {"title": "\u767d\u5170\u82b1", "artist": ["\u6797\u4fca\u6770"], "file": "\u6797\u4fca\u6770 - \u767d\u5170\u82b1.mp3", "storage": "music1"}, {"title": "\u767d\u7f8a\u68a6", "artist": ["\u6797\u4fca\u6770"], "file": "\u6797\u4fca\u6770 - \u767d\u7f8a\u68a6.mp3", "storage": "music1"}, {"title": "\u76d7", "artist": ["\u6797\u4fca\u6770"], "file": "\u6797\u4fca\u6770 - \u76d7.mp3", "storage": "music1"}, {"title": "\u76f8\u4fe1\u65e0\u9650", "artist": ["\u6797\u4fca\u6770"], "file": "\u6797\u4fca\u6770 - \u76f8\u4fe1\u65e0\u9650.mp3", "storage": "music1"}, {"title": "\u7a7f\u8d8a", "artist": ["\u6797\u4fca\u6770"], "file": "\u6797\u4fca\u6770 - \u7a7f\u8d8a.mp3", "storage": "music1"}, {"title": "\u7a81\u7136\u7d2f\u4e86", "artist": ["\u6797\u4fca\u6770"], "file": "\u6797\u4fca\u6770 - \u7a81\u7136\u7d2f\u4e86.mp3", "storage": "music1"}, {"title": "\u7b2c\u4e8c\u5929\u5802", "artist": ["\u6797\u4fca\u6770"], "file": "\u6797\u4fca\u6770 - \u7b2c\u4e8c\u5929\u5802.mp3", "storage": "music1"}, {"title": "\u7b2c\u51e0\u4e2a100\u5929", "artist": ["\u6797\u4fca\u6770"], "file": "\u6797\u4fca\u6770 - \u7b2c\u51e0\u4e2a100\u5929.mp3", "storage": "music1"}, {"title": "\u7b80\u7b80\u5355\u5355", "artist": ["\u6797\u4fca\u6770"], "file": "\u6797\u4fca\u6770 - \u7b80\u7b80\u5355\u5355.mp3", "storage": "music1"}, {"title": "\u7cbe\u7075", "artist": ["\u6797\u4fca\u6770"], "file": "\u6797\u4fca\u6770 - \u7cbe\u7075.mp3", "storage": "music1"}, {"title": "\u7f16\u53f789757", "artist": ["\u6797\u4fca\u6770"], "file": "\u6797\u4fca\u6770 - \u7f16\u53f789757.mp3", "storage": "music1"}, {"title": "\u7f8e\u4eba\u9c7c", "artist": ["\u6797\u4fca\u6770"], "file": "\u6797\u4fca\u6770 - \u7f8e\u4eba\u9c7c.mp3", "storage": "music1"}, {"title": "\u7fc5\u8180", "artist": ["\u6797\u4fca\u6770"], "file": "\u6797\u4fca\u6770 - \u7fc5\u8180.mp3", "storage": "music1"}, {"title": "\u80cc\u5bf9\u80cc\u62e5\u62b1", "artist": ["\u6797\u4fca\u6770"], "file": "\u6797\u4fca\u6770 - \u80cc\u5bf9\u80cc\u62e5\u62b1.mp3", "storage": "music1"}, {"title": "\u81ea\u7531\u4e0d\u53d8", "artist": ["\u6797\u4fca\u6770"], "file": "\u6797\u4fca\u6770 - \u81ea\u7531\u4e0d\u53d8.mp3", "storage": "music1"}, {"title": "\u8309\u8389\u96e8", "artist": ["\u6797\u4fca\u6770"], "file": "\u6797\u4fca\u6770 - \u8309\u8389\u96e8.mp3", "storage": "music1"}, {"title": "\u838e\u58eb\u6bd4\u4e9a\u7684\u5929\u4efd", "artist": ["\u6797\u4fca\u6770"], "file": "\u6797\u4fca\u6770 - \u838e\u58eb\u6bd4\u4e9a\u7684\u5929\u4efd.mp3", "storage": "music1"}, {"title": "\u838e\u90ce\u563f\u5466 \u53ea\u5bf9\u4f60\u8bf4", "artist": ["\u6797\u4fca\u6770"], "file": "\u6797\u4fca\u6770 - \u838e\u90ce\u563f\u5466 \u53ea\u5bf9\u4f60\u8bf4.mp3", "storage": "music1"}, {"title": "\u8857\u9053", "artist": ["\u6797\u4fca\u6770"], "file": "\u6797\u4fca\u6770 - \u8857\u9053.mp3", "storage": "music1"}, {"title": "\u88c2\u7f1d\u4e2d\u7684\u9633\u5149", "artist": ["\u6797\u4fca\u6770"], "file": "\u6797\u4fca\u6770 - \u88c2\u7f1d\u4e2d\u7684\u9633\u5149.mp3", "storage": "music1"}, {"title": "\u897f\u754c", "artist": ["\u6797\u4fca\u6770"], "file": "\u6797\u4fca\u6770 - \u897f\u754c.mp3", "storage": "music1"}, {"title": "\u8ba9\u6211\u5fc3\u52a8\u7684\u4eba", "artist": ["\u6797\u4fca\u6770"], "file": "\u6797\u4fca\u6770 - \u8ba9\u6211\u5fc3\u52a8\u7684\u4eba.mp3", "storage": "music1"}, {"title": "\u8bb0\u5f97", "artist": ["\u6797\u4fca\u6770"], "file": "\u6797\u4fca\u6770 - \u8bb0\u5f97.mp3", "storage": "music1"}, {"title": "\u8c46\u6d46\u6cb9\u6761", "artist": ["\u6797\u4fca\u6770"], "file": "\u6797\u4fca\u6770 - \u8c46\u6d46\u6cb9\u6761.mp3", "storage": "music1"}, {"title": "\u8d77\u5e8a\u4e86", "artist": ["\u6797\u4fca\u6770"], "file": "\u6797\u4fca\u6770 - \u8d77\u5e8a\u4e86.mp3", "storage": "music1"}, {"title": "\u8ddd\u79bb", "artist": ["\u6797\u4fca\u6770"], "file": "\u6797\u4fca\u6770 - \u8ddd\u79bb.mp3", "storage": "music1"}, {"title": "\u8ddf\u5c41\u866b", "artist": ["\u6797\u4fca\u6770"], "file": "\u6797\u4fca\u6770 - \u8ddf\u5c41\u866b.mp3", "storage": "music1"}, {"title": "\u8eab\u4e3a\u98ce\u5e06", "artist": ["\u6797\u4fca\u6770"], "file": "\u6797\u4fca\u6770 - \u8eab\u4e3a\u98ce\u5e06.mp3", "storage": "music1"}, {"title": "\u8f6c\u52a8", "artist": ["\u6797\u4fca\u6770"], "file": "\u6797\u4fca\u6770 - \u8f6c\u52a8.mp3", "storage": "music1"}, {"title": "\u8fdb\u5316\u8bba", "artist": ["\u6797\u4fca\u6770"], "file": "\u6797\u4fca\u6770 - \u8fdb\u5316\u8bba.mp3", "storage": "music1"}, {"title": "\u90a3\u4e9b\u4f60\u5f88\u5192\u9669\u7684\u68a6", "artist": ["\u6797\u4fca\u6770"], "file": "\u6797\u4fca\u6770 - \u90a3\u4e9b\u4f60\u5f88\u5192\u9669\u7684\u68a6.mp3", "storage": "music1"}, {"title": "\u9189\u8d64\u58c1", "artist": ["\u6797\u4fca\u6770"], "file": "\u6797\u4fca\u6770 - \u9189\u8d64\u58c1.mp3", "storage": "music1"}, {"title": "\u964c\u751f\u8001\u670b\u53cb", "artist": ["\u6797\u4fca\u6770"], "file": "\u6797\u4fca\u6770 - \u964c\u751f\u8001\u670b\u53cb.mp3", "storage": "music1"}, {"title": "\u96f6\u5ea6\u7684\u4eb2\u543b", "artist": ["\u6797\u4fca\u6770"], "file": "\u6797\u4fca\u6770 - \u96f6\u5ea6\u7684\u4eb2\u543b.mp3", "storage": "music1"}, {"title": "\u9ed1\u591c\u95ee\u767d\u5929", "artist": ["\u6797\u4fca\u6770"], "file": "\u6797\u4fca\u6770 - \u9ed1\u591c\u95ee\u767d\u5929.mp3", "storage": "music1"}, {"title": "\u9ed1\u6b66\u58eb", "artist": ["\u6797\u4fca\u6770"], "file": "\u6797\u4fca\u6770 - \u9ed1\u6b66\u58eb.mp3", "storage": "music1"}, {"title": "\u9ed1\u952e", "artist": ["\u6797\u4fca\u6770"], "file": "\u6797\u4fca\u6770 - \u9ed1\u952e.mp3", "storage": "music1"}, {"title": "\u4e39\u5b81\u6267\u7740", "artist": ["\u6797\u4fca\u6770&\u6d88\u9664\u8054\u840c"], "file": "\u6797\u4fca\u6770&\u6d88\u9664\u8054\u840c - \u4e39\u5b81\u6267\u7740.mp3", "storage": "music1"}, {"title": "I Am Alive", "artist": ["\u6797\u4fca\u6770", "Jason Mraz"], "file": "\u6797\u4fca\u6770.Jason Mraz - I Am Alive.mp3", "storage": "music1"}, {"title": "\u4e3b\u89d2", "artist": ["\u6797\u4fca\u6770", "Machi"], "file": "\u6797\u4fca\u6770.Machi - \u4e3b\u89d2.mp3", "storage": "music1"}, {"title": "\u52a0\u6cb9\uff01", "artist": ["\u6797\u4fca\u6770", "MC Hotdog"], "file": "\u6797\u4fca\u6770.MC Hotdog - \u52a0\u6cb9\uff01.mp3", "storage": "music1"}, {"title": "\u9ed1\u6697\u9a91\u58eb", "artist": ["\u6797\u4fca\u6770", "\u4e94\u6708\u5929"], "file": "\u6797\u4fca\u6770.\u4e94\u6708\u5929 - \u9ed1\u6697\u9a91\u58eb.mp3", "storage": "music1"}, {"title": "\u7531\u4f60\u9009\u62e9", "artist": ["\u6797\u4fca\u6770", "\u519c\u592bFama"], "file": "\u6797\u4fca\u6770.\u519c\u592bFama - \u7531\u4f60\u9009\u62e9.mp3", "storage": "music1"}, {"title": "\u8868\u8fbe\u7231", "artist": ["\u6797\u4fca\u6770", "\u5ed6\u541b"], "file": "\u6797\u4fca\u6770.\u5ed6\u541b - \u8868\u8fbe\u7231.mp3", "storage": "music1"}, {"title": "\u6709\u68a6\u4e0d\u96be", "artist": ["\u6797\u4fca\u6770", "\u5f20\u6000\u98a2", "\u5468\u4fe1\u5ef7"], "file": "\u6797\u4fca\u6770.\u5f20\u6000\u98a2.\u5468\u4fe1\u5ef7 - \u6709\u68a6\u4e0d\u96be.mp3", "storage": "music1"}, {"title": "\u4fdd\u62a4\u8272", "artist": ["\u6797\u4fca\u6770", "\u5f20\u97f6\u6db5"], "file": "\u6797\u4fca\u6770.\u5f20\u97f6\u6db5 - \u4fdd\u62a4\u8272.mp3", "storage": "music1"}, {"title": "\u53cb\u4eba\u8bf4", "artist": ["\u6797\u4fca\u6770", "\u6000\u79cb"], "file": "\u6797\u4fca\u6770.\u6000\u79cb - \u53cb\u4eba\u8bf4.mp3", "storage": "music1"}, {"title": "\u98de\u673a", "artist": ["\u6797\u4fca\u6770", "\u6797\u4fca\u5cf0"], "file": "\u6797\u4fca\u6770.\u6797\u4fca\u5cf0 - \u98de\u673a.mp3", "storage": "music1"}, {"title": "L-O-V-E", "artist": ["\u6797\u4fca\u6770", "\u6d2a\u4fca\u626c"], "file": "\u6797\u4fca\u6770.\u6d2a\u4fca\u626c - L-O-V-E.mp3", "storage": "music1"}, {"title": "\u73b0\u5728\u7684\u6211\u548c\u5979", "artist": ["\u6797\u4fca\u6770", "\u8303\u7ef4\u4ec1"], "file": "\u6797\u4fca\u6770.\u8303\u7ef4\u4ec1 - \u73b0\u5728\u7684\u6211\u548c\u5979.mp3", "storage": "music1"}, {"title": "\u5c0f\u9152\u7a9d", "artist": ["\u6797\u4fca\u6770", "\u8521\u5353\u598d"], "file": "\u6797\u4fca\u6770.\u8521\u5353\u598d - \u5c0f\u9152\u7a9d.mp3", "storage": "music1"}, {"title": "\u624b\u5fc3\u7684\u8537\u8587", "artist": ["\u6797\u4fca\u6770", "\u9093\u7d2b\u68cb"], "file": "\u6797\u4fca\u6770.\u9093\u7d2b\u68cb - \u624b\u5fc3\u7684\u8537\u8587.mp3", "storage": "music1"}, {"title": "\u7231\u4e0e\u5e0c\u671b", "artist": ["\u6797\u4fca\u6770", "\u91cd\u5e86\u5e02\u9752\u5c11\u5e74\u5bab\u94f6\u674f\u7ae5\u58f0\u5408\u5531\u56e2"], "file": "\u6797\u4fca\u6770.\u91cd\u5e86\u5e02\u9752\u5c11\u5e74\u5bab\u94f6\u674f\u7ae5\u58f0\u5408\u5531\u56e2 - \u7231\u4e0e\u5e0c\u671b.mp3", "storage": "music1"}, {"title": "\u53d1\u73b0\u7231", "artist": ["\u6797\u4fca\u6770", "\u91d1\u838e"], "file": "\u6797\u4fca\u6770.\u91d1\u838e - \u53d1\u73b0\u7231.mp3", "storage": "music1"}, {"title": "\u671f\u5f85\u7231", "artist": ["\u6797\u4fca\u6770", "\u91d1\u838e"], "file": "\u6797\u4fca\u6770.\u91d1\u838e - \u671f\u5f85\u7231.mp3", "storage": "music1"}, {"title": "\u5355\u8eab\u60c5\u6b4c", "artist": ["\u6797\u5fd7\u70ab"], "file": "\u6797\u5fd7\u70ab - \u5355\u8eab\u60c5\u6b4c.mp3", "storage": "music1"}, {"title": "\u708e\u590f\u4ee4", "artist": ["\u6797\u659c\u9633"], "file": "\u6797\u659c\u9633 - \u708e\u590f\u4ee4.mp3", "storage": "music1"}, {"title": "\u4e00\u751f\u6709\u4f60", "artist": ["\u6c34\u6728\u5e74\u534e"], "file": "\u6c34\u6728\u5e74\u534e - \u4e00\u751f\u6709\u4f60.mp3", "storage": "music1"}, {"title": "\u5728\u4ed6\u4e61", "artist": ["\u6c34\u6728\u5e74\u534e"], "file": "\u6c34\u6728\u5e74\u534e - \u5728\u4ed6\u4e61.mp3", "storage": "music1"}, {"title": "\u50cf\u68a6\u4e00\u6837\u81ea\u7531", "artist": ["\u6c6a\u5cf0"], "file": "\u6c6a\u5cf0 - \u50cf\u68a6\u4e00\u6837\u81ea\u7531.mp3", "storage": "music1"}, {"title": "\u5317\u4eac\u5317\u4eac", "artist": ["\u6c6a\u5cf0"], "file": "\u6c6a\u5cf0 - \u5317\u4eac\u5317\u4eac.mp3", "storage": "music1"}, {"title": "\u5728\u96e8\u4e2d", "artist": ["\u6c6a\u5cf0"], "file": "\u6c6a\u5cf0 - \u5728\u96e8\u4e2d.mp3", "storage": "music1"}, {"title": "\u57ce\u5e02\u4e4b\u5149", "artist": ["\u6c6a\u5cf0"], "file": "\u6c6a\u5cf0 - \u57ce\u5e02\u4e4b\u5149.mp3", "storage": "music1"}, {"title": "\u5b58\u5728", "artist": ["\u6c6a\u5cf0"], "file": "\u6c6a\u5cf0 - \u5b58\u5728.mp3", "storage": "music1"}, {"title": "\u5c18\u571f", "artist": ["\u6c6a\u5cf0"], "file": "\u6c6a\u5cf0 - \u5c18\u571f.mp3", "storage": "music1"}, {"title": "\u5f53\u6211\u60f3\u4f60\u7684\u65f6\u5019", "artist": ["\u6c6a\u5cf0"], "file": "\u6c6a\u5cf0 - \u5f53\u6211\u60f3\u4f60\u7684\u65f6\u5019.mp3", "storage": "music1"}, {"title": "\u6012\u653e\u7684\u751f\u547d", "artist": ["\u6c6a\u5cf0"], "file": "\u6c6a\u5cf0 - \u6012\u653e\u7684\u751f\u547d.mp3", "storage": "music1"}, {"title": "\u6211\u7231\u4f60\uff0c\u751f\u6d3b", "artist": ["\u6c6a\u5cf0"], "file": "\u6c6a\u5cf0 - \u6211\u7231\u4f60\uff0c\u751f\u6d3b.mp3", "storage": "music1"}, {"title": "\u6539\u53d8", "artist": ["\u6c6a\u5cf0"], "file": "\u6c6a\u5cf0 - \u6539\u53d8.mp3", "storage": "music1"}, {"title": "\u6625\u5929\u91cc", "artist": ["\u6c6a\u5cf0"], "file": "\u6c6a\u5cf0 - \u6625\u5929\u91cc.mp3", "storage": "music1"}, {"title": "\u751f\u6765\u5b64\u72ec", "artist": ["\u6c6a\u5cf0"], "file": "\u6c6a\u5cf0 - \u751f\u6765\u5b64\u72ec.mp3", "storage": "music1"}, {"title": "\u751f\u6765\u5f77\u5fa8", "artist": ["\u6c6a\u5cf0"], "file": "\u6c6a\u5cf0 - \u751f\u6765\u5f77\u5fa8.mp3", "storage": "music1"}, {"title": "\u788e\u68a6", "artist": ["\u6c6a\u5cf0"], "file": "\u6c6a\u5cf0 - \u788e\u68a6.mp3", "storage": "music1"}, {"title": "\u7f8e\u4e3d\u4e16\u754c\u7684\u5b64\u513f", "artist": ["\u6c6a\u5cf0"], "file": "\u6c6a\u5cf0 - \u7f8e\u4e3d\u4e16\u754c\u7684\u5b64\u513f.mp3", "storage": "music1"}, {"title": "\u82b1\u706b", "artist": ["\u6c6a\u5cf0"], "file": "\u6c6a\u5cf0 - \u82b1\u706b.mp3", "storage": "music1"}, {"title": "\u8bf7\u628a\u6211\u5728\u8def\u4e0a\u53eb\u9192", "artist": ["\u6c6a\u5cf0"], "file": "\u6c6a\u5cf0 - \u8bf7\u628a\u6211\u5728\u8def\u4e0a\u53eb\u9192.mp3", "storage": "music1"}, {"title": "\u8d2b\u7620\u4e4b\u6b4c", "artist": ["\u6c6a\u5cf0"], "file": "\u6c6a\u5cf0 - \u8d2b\u7620\u4e4b\u6b4c.mp3", "storage": "music1"}, {"title": "\u8ff7\u9e7f", "artist": ["\u6c6a\u5cf0"], "file": "\u6c6a\u5cf0 - \u8ff7\u9e7f.mp3", "storage": "music1"}, {"title": "\u9752\u6625", "artist": ["\u6c6a\u5cf0"], "file": "\u6c6a\u5cf0 - \u9752\u6625.mp3", "storage": "music1"}, {"title": "\u98de\u5f97\u66f4\u9ad8", "artist": ["\u6c6a\u5cf0"], "file": "\u6c6a\u5cf0 - \u98de\u5f97\u66f4\u9ad8.mp3", "storage": "music1"}, {"title": "\u4f9d\u7136\u7231\u4f60", "artist": ["\u738b\u529b\u5b8f"], "file": "\u738b\u529b\u5b8f - \u4f9d\u7136\u7231\u4f60.mp3", "storage": "music1"}, {"title": "\u552f\u4e00", "artist": ["\u738b\u529b\u5b8f"], "file": "\u738b\u529b\u5b8f - \u552f\u4e00.mp3", "storage": "music1"}, {"title": "\u5927\u57ce\u5c0f\u7231", "artist": ["\u738b\u529b\u5b8f"], "file": "\u738b\u529b\u5b8f - \u5927\u57ce\u5c0f\u7231.mp3", "storage": "music1"}, {"title": "\u6211\u4eec\u7684\u6b4c", "artist": ["\u738b\u529b\u5b8f"], "file": "\u738b\u529b\u5b8f - \u6211\u4eec\u7684\u6b4c.mp3", "storage": "music1"}, {"title": "\u6539\u53d8\u81ea\u5df1", "artist": ["\u738b\u529b\u5b8f"], "file": "\u738b\u529b\u5b8f - \u6539\u53d8\u81ea\u5df1.mp3", "storage": "music1"}, {"title": "\u82b1\u7530\u9519", "artist": ["\u738b\u529b\u5b8f"], "file": "\u738b\u529b\u5b8f - \u82b1\u7530\u9519.mp3", "storage": "music1"}, {"title": "\u9f99\u7684\u4f20\u4eba", "artist": ["\u738b\u529b\u5b8f"], "file": "\u738b\u529b\u5b8f - \u9f99\u7684\u4f20\u4eba.mp3", "storage": "music1"}, {"title": "\u53e6\u4e00\u4e2a\u5929\u5802", "artist": ["\u738b\u529b\u5b8f\u3001\u5f20\u9753\u9896"], "file": "\u738b\u529b\u5b8f\u3001\u5f20\u9753\u9896 - \u53e6\u4e00\u4e2a\u5929\u5802.mp3", "storage": "music1"}, {"title": "\u5979", "artist": ["\u738b\u5a01"], "file": "\u738b\u5a01 - \u5979.mp3", "storage": "music1"}, {"title": "\u79cb\u5929\u4e0d\u56de\u6765", "artist": ["\u738b\u5f3a"], "file": "\u738b\u5f3a - \u79cb\u5929\u4e0d\u56de\u6765.mp3", "storage": "music1"}, {"title": "\u6211\u4f1a\u597d\u597d\u7684", "artist": ["\u738b\u5fc3\u51cc"], "file": "\u738b\u5fc3\u51cc - \u6211\u4f1a\u597d\u597d\u7684.mp3", "storage": "music1"}, {"title": "\u6708\u5149", "artist": ["\u738b\u5fc3\u51cc"], "file": "\u738b\u5fc3\u51cc - \u6708\u5149.mp3", "storage": "music1"}, {"title": "\u776b\u6bdb\u5f2f\u5f2f", "artist": ["\u738b\u5fc3\u51cc"], "file": "\u738b\u5fc3\u51cc - \u776b\u6bdb\u5f2f\u5f2f.mp3", "storage": "music1"}, {"title": "\u7b2c\u4e00\u6b21\u7231\u7684\u4eba", "artist": ["\u738b\u5fc3\u51cc"], "file": "\u738b\u5fc3\u51cc - \u7b2c\u4e00\u6b21\u7231\u7684\u4eba.mp3", "storage": "music1"}, {"title": "\u7fbd\u6bdb", "artist": ["\u738b\u5fc3\u51cc"], "file": "\u738b\u5fc3\u51cc - \u7fbd\u6bdb.mp3", "storage": "music1"}, {"title": "\u7fc5\u8180", "artist": ["\u738b\u5fc3\u51cc"], "file": "\u738b\u5fc3\u51cc - \u7fc5\u8180.mp3", "storage": "music1"}, {"title": "\u90a3\u5e74\u590f\u5929\u5b81\u9759\u7684\u6d77", "artist": ["\u738b\u5fc3\u51cc"], "file": "\u738b\u5fc3\u51cc - \u90a3\u5e74\u590f\u5929\u5b81\u9759\u7684\u6d77.mp3", "storage": "music1"}, {"title": "\u9752\u6625\u8003\u5377", "artist": ["\u738b\u5fc3\u51cc"], "file": "\u738b\u5fc3\u51cc - \u9752\u6625\u8003\u5377.mp3", "storage": "music1"}, {"title": "\u98d8\u98d8", "artist": ["\u738b\u5fc3\u51cc"], "file": "\u738b\u5fc3\u51cc - \u98d8\u98d8.mp3", "storage": "music1"}, {"title": "\u4eba\u95f4", "artist": ["\u738b\u83f2"], "file": "\u738b\u83f2 - \u4eba\u95f4.mp3", "storage": "music1"}, {"title": "\u52ff\u52ff\u90a3\u5e74", "artist": ["\u738b\u83f2"], "file": "\u738b\u83f2 - \u52ff\u52ff\u90a3\u5e74.mp3", "storage": "music1"}, {"title": "\u56e0\u4e3a\u7231\u60c5", "artist": ["\u738b\u83f2"], "file": "\u738b\u83f2 - \u56e0\u4e3a\u7231\u60c5.mp3", "storage": "music1"}, {"title": "\u6000\u5ff5", "artist": ["\u738b\u83f2"], "file": "\u738b\u83f2 - \u6000\u5ff5.mp3", "storage": "music1"}, {"title": "\u65cb\u6728", "artist": ["\u738b\u83f2"], "file": "\u738b\u83f2 - \u65cb\u6728.mp3", "storage": "music1"}, {"title": "\u6d41\u5e74", "artist": ["\u738b\u83f2"], "file": "\u738b\u83f2 - \u6d41\u5e74.mp3", "storage": "music1"}, {"title": "\u7ea2\u8c46", "artist": ["\u738b\u83f2"], "file": "\u738b\u83f2 - \u7ea2\u8c46.mp3", "storage": "music1"}, {"title": "\u5929\u30ce\u5f31", "artist": ["\u7ed8\u68a8\u8863"], "file": "\u7ed8\u68a8\u8863 - \u5929\u30ce\u5f31.mp3", "storage": "music1"}, {"title": "\u7cbe\u821e\u95e8", "artist": ["\u7f57\u5fd7\u7965"], "file": "\u7f57\u5fd7\u7965 - \u7cbe\u821e\u95e8.mp3", "storage": "music1"}, {"title": "\u5317\u4eac\u6b22\u8fce\u4f60", "artist": ["\u7fa4\u661f"], "file": "\u7fa4\u661f - \u5317\u4eac\u6b22\u8fce\u4f60.mp3", "storage": "music1"}, {"title": "\u660e\u5929\u4f1a\u66f4\u597d", "artist": ["\u7fa4\u661f"], "file": "\u7fa4\u661f - \u660e\u5929\u4f1a\u66f4\u597d.mp3", "storage": "music1"}, {"title": "Beautiful Love", "artist": ["\u8521\u5065\u96c5"], "file": "\u8521\u5065\u96c5 - Beautiful Love.mp3", "storage": "music1"}, {"title": "\u7ea2\u8272\u9ad8\u8ddf\u978b", "artist": ["\u8521\u5065\u96c5"], "file": "\u8521\u5065\u96c5 - \u7ea2\u8272\u9ad8\u8ddf\u978b.mp3", "storage": "music1"}, {"title": "\u73ab\u7470", "artist": ["\u8d30\u4f70"], "file": "\u8d30\u4f70 - \u73ab\u7470.mp3", "storage": "music1"}, {"title": "\u591c\u7a7a\u4e2d\u6700\u4eae\u7684\u661f", "artist": ["\u9003\u8dd1\u8ba1\u5212"], "file": "\u9003\u8dd1\u8ba1\u5212 - \u591c\u7a7a\u4e2d\u6700\u4eae\u7684\u661f.mp3", "storage": "music1"}, {"title": "\u5f81\u670d", "artist": ["\u90a3\u82f1"], "file": "\u90a3\u82f1 - \u5f81\u670d.mp3", "storage": "music1"}, {"title": "\u767d\u5929\u4e0d\u61c2\u591c\u7684\u9ed1", "artist": ["\u90a3\u82f1"], "file": "\u90a3\u82f1 - \u767d\u5929\u4e0d\u61c2\u591c\u7684\u9ed1.mp3", "storage": "music1"}, {"title": "\u9ed8", "artist": ["\u90a3\u82f1"], "file": "\u90a3\u82f1 - \u9ed8.mp3", "storage": "music1"}, {"title": "\u4e0b\u4e00\u4e2a\u5929\u4eae", "artist": ["\u90ed\u9759"], "file": "\u90ed\u9759 - \u4e0b\u4e00\u4e2a\u5929\u4eae.mp3", "storage": "music1"}, {"title": "\u661f\u6708\u795e\u8bdd", "artist": ["\u91d1\u838e"], "file": "\u91d1\u838e - \u661f\u6708\u795e\u8bdd.mp3", "storage": "music1"}, {"title": "\u6700\u540e\u4e00\u4e2a\u590f\u5929", "artist": ["\u91d1\u838e"], "file": "\u91d1\u838e - \u6700\u540e\u4e00\u4e2a\u590f\u5929.mp3", "storage": "music1"}, {"title": "\u6e34\u671b", "artist": ["\u91d1\u838e"], "file": "\u91d1\u838e - \u6e34\u671b.mp3", "storage": "music1"}, {"title": "\u7231\u7684\u9b54\u6cd5", "artist": ["\u91d1\u838e"], "file": "\u91d1\u838e - \u7231\u7684\u9b54\u6cd5.mp3", "storage": "music1"}, {"title": "\u9c7c\u7384\u673a", "artist": ["\u9526\u96f6"], "file": "\u9526\u96f6 - \u9c7c\u7384\u673a.mp3", "storage": "music1"}, {"title": "\u5343\u53e4", "artist": ["\u963f\u5170"], "file": "\u963f\u5170 - \u5343\u53e4.mp3", "storage": "music1"}, {"title": "Andy", "artist": ["\u963f\u675c"], "file": "\u963f\u675c - Andy.mp3", "storage": "music1"}, {"title": "\u4f60\u5c31\u50cf\u4e2a\u5c0f\u5b69", "artist": ["\u963f\u675c"], "file": "\u963f\u675c - \u4f60\u5c31\u50cf\u4e2a\u5c0f\u5b69.mp3", "storage": "music1"}, {"title": "\u575a\u6301\u5230\u5e95", "artist": ["\u963f\u675c"], "file": "\u963f\u675c - \u575a\u6301\u5230\u5e95.mp3", "storage": "music1"}, {"title": "\u79bb\u522b", "artist": ["\u963f\u675c"], "file": "\u963f\u675c - \u79bb\u522b.mp3", "storage": "music1"}, {"title": "\u6c27\u6c14", "artist": ["\u963f\u6cf1"], "file": "\u963f\u6cf1 - \u6c27\u6c14.mp3", "storage": "music1"}, {"title": "\u6b6a\u6b6a\uff1f", "artist": ["\u963f\u9896\u4e0d\u8bf4\u8bdd"], "file": "\u963f\u9896\u4e0d\u8bf4\u8bdd - \u6b6a\u6b6a\uff1f.mp3", "storage": "music1"}, {"title": "\u597d\u4e45\u4e0d\u89c1", "artist": ["\u9648\u5955\u8fc5"], "file": "\u9648\u5955\u8fc5 - \u597d\u4e45\u4e0d\u89c1.mp3", "storage": "music1"}, {"title": "\u7231\u60c5\u8f6c\u79fb", "artist": ["\u9648\u5955\u8fc5"], "file": "\u9648\u5955\u8fc5 - \u7231\u60c5\u8f6c\u79fb.mp3", "storage": "music1"}, {"title": "\u7ea2\u73ab\u7470", "artist": ["\u9648\u5955\u8fc5"], "file": "\u9648\u5955\u8fc5 - \u7ea2\u73ab\u7470.mp3", "storage": "music1"}, {"title": "\u6d4e\u5357\u6d4e\u5357", "artist": ["\u9648\u5c0f\u718a"], "file": "\u9648\u5c0f\u718a - \u6d4e\u5357\u6d4e\u5357.mp3", "storage": "music1"}, {"title": "\u5149", "artist": ["\u9648\u7c92"], "file": "\u9648\u7c92 - \u5149.mp3", "storage": "music1"}, {"title": "\u5947\u5999\u80fd\u529b\u6b4c", "artist": ["\u9648\u7c92"], "file": "\u9648\u7c92 - \u5947\u5999\u80fd\u529b\u6b4c.mp3", "storage": "music1"}, {"title": "\u5c0f\u534a", "artist": ["\u9648\u7c92"], "file": "\u9648\u7c92 - \u5c0f\u534a.mp3", "storage": "music1"}, {"title": "\u6613\u71c3\u6613\u7206\u70b8", "artist": ["\u9648\u7c92"], "file": "\u9648\u7c92 - \u6613\u71c3\u6613\u7206\u70b8.mp3", "storage": "music1"}, {"title": "\u4f60\u7684\u9152\u9986\u5bf9\u6211\u6253\u4e86\u70ca", "artist": ["\u9648\u96ea\u51dd"], "file": "\u9648\u96ea\u51dd - \u4f60\u7684\u9152\u9986\u5bf9\u6211\u6253\u4e86\u70ca.mp3", "storage": "music1"}, {"title": "\u5047\u88c5", "artist": ["\u9648\u96ea\u51dd"], "file": "\u9648\u96ea\u51dd - \u5047\u88c5.mp3", "storage": "music1"}, {"title": "\u7eff\u8272", "artist": ["\u9648\u96ea\u51dd"], "file": "\u9648\u96ea\u51dd - \u7eff\u8272.mp3", "storage": "music1"}, {"title": "\u7406\u60f3\u4e09\u65ec", "artist": ["\u9648\u9e3f\u5b87"], "file": "\u9648\u9e3f\u5b87 - \u7406\u60f3\u4e09\u65ec.mp3", "storage": "music1"}, {"title": "\u9014\u4e2d", "artist": ["\u9648\u9e3f\u5b87"], "file": "\u9648\u9e3f\u5b87 - \u9014\u4e2d.mp3", "storage": "music1"}, {"title": "\u5c0f\u57ce\u8c23", "artist": ["\u97f6\u534e"], "file": "\u97f6\u534e - \u5c0f\u57ce\u8c23.mp3", "storage": "music1"}, {"title": "\u50b2\u5bd2", "artist": ["\u9a6c\u9814"], "file": "\u9a6c\u9814 - \u50b2\u5bd2.mp3", "storage": "music1"}, {"title": "\u70df\u96e8\u5c0f\u5df7", "artist": ["\u9ec4\u777f\u94ed"], "file": "\u9ec4\u777f\u94ed - \u70df\u96e8\u5c0f\u5df7.mp3", "storage": "music1"}, {"title": "\u632a\u5a01\u7684\u68ee\u6797", "artist": ["\u4f0d\u4f70"], "file": "\u4f0d\u4f70 - \u632a\u5a01\u7684\u68ee\u6797.mp3", "storage": "music2"}, {"title": "\u5bc2\u5bde\u6c99\u6d32\u51b7", "artist": ["\u5468\u4f20\u96c4"], "file": "\u5468\u4f20\u96c4 - \u5bc2\u5bde\u6c99\u6d32\u51b7.mp3", "storage": "music2"}, {"title": "\u9ec4\u660f", "artist": ["\u5468\u4f20\u96c4"], "file": "\u5468\u4f20\u96c4 - \u9ec4\u660f.mp3", "storage": "music2"}, {"title": "\u670b\u53cb", "artist": ["\u5468\u534e\u5065"], "file": "\u5468\u534e\u5065 - \u670b\u53cb.mp3", "storage": "music2"}, {"title": "\u771f\u5fc3\u82f1\u96c4", "artist": ["\u5468\u534e\u5065"], "file": "\u5468\u534e\u5065 - \u771f\u5fc3\u82f1\u96c4.mp3", "storage": "music2"}, {"title": "\u98ce\u96e8\u65e0\u963b", "artist": ["\u5468\u534e\u5065"], "file": "\u5468\u534e\u5065 - \u98ce\u96e8\u65e0\u963b.mp3", "storage": "music2"}, {"title": "Mine Mine", "artist": ["\u5468\u6770\u4f26"], "file": "\u5468\u6770\u4f26 - Mine Mine.mp3", "storage": "music2"}, {"title": "Now You See Me", "artist": ["\u5468\u6770\u4f26"], "file": "\u5468\u6770\u4f26 - Now You See Me.mp3", "storage": "music2"}, {"title": "\u4e00\u53e3\u6c14\u5168\u5ff5\u5bf9", "artist": ["\u5468\u6770\u4f26"], "file": "\u5468\u6770\u4f26 - \u4e00\u53e3\u6c14\u5168\u5ff5\u5bf9.mp3", "storage": "music2"}, {"title": "\u4e00\u70b9\u70b9", "artist": ["\u5468\u6770\u4f26"], "file": "\u5468\u6770\u4f26 - \u4e00\u70b9\u70b9.mp3", "storage": "music2"}, {"title": "\u4e00\u8def\u5411\u5317", "artist": ["\u5468\u6770\u4f26"], "file": "\u5468\u6770\u4f26 - \u4e00\u8def\u5411\u5317.mp3", "storage": "music2"}, {"title": "\u4e03\u91cc\u9999", "artist": ["\u5468\u6770\u4f26"], "file": "\u5468\u6770\u4f26 - \u4e03\u91cc\u9999.mp3", "storage": "music2"}, {"title": "\u4e09\u5e74\u4e8c\u73ed", "artist": ["\u5468\u6770\u4f26"], "file": "\u5468\u6770\u4f26 - \u4e09\u5e74\u4e8c\u73ed.mp3", "storage": "music2"}, {"title": "\u4e0a\u6d77\u4e00\u4e5d\u56db\u4e09", "artist": ["\u5468\u6770\u4f26"], "file": "\u5468\u6770\u4f26 - \u4e0a\u6d77\u4e00\u4e5d\u56db\u4e09.mp3", "storage": "music2"}, {"title": "\u4e16\u754c\u672a\u672b\u65e5", "artist": ["\u5468\u6770\u4f26"], "file": "\u5468\u6770\u4f26 - \u4e16\u754c\u672a\u672b\u65e5.mp3", "storage": "music2"}, {"title": "\u4e16\u754c\u672b\u65e5", "artist": ["\u5468\u6770\u4f26"], "file": "\u5468\u6770\u4f26 - \u4e16\u754c\u672b\u65e5.mp3", "storage": "music2"}, {"title": "\u4e1c\u98ce\u7834", "artist": ["\u5468\u6770\u4f26"], "file": "\u5468\u6770\u4f26 - \u4e1c\u98ce\u7834.mp3", "storage": "music2"}, {"title": "\u4e4c\u514b\u4e3d\u4e3d", "artist": ["\u5468\u6770\u4f26"], "file": "\u5468\u6770\u4f26 - \u4e4c\u514b\u4e3d\u4e3d.mp3", "storage": "music2"}, {"title": "\u4e54\u514b\u53d4\u53d4", "artist": ["\u5468\u6770\u4f26"], "file": "\u5468\u6770\u4f26 - \u4e54\u514b\u53d4\u53d4.mp3", "storage": "music2"}, {"title": "\u4e71\u821e\u6625\u79cb", "artist": ["\u5468\u6770\u4f26"], "file": "\u5468\u6770\u4f26 - \u4e71\u821e\u6625\u79cb.mp3", "storage": "music2"}, {"title": "\u4ee5\u7236\u4e4b\u540d", "artist": ["\u5468\u6770\u4f26"], "file": "\u5468\u6770\u4f26 - \u4ee5\u7236\u4e4b\u540d.mp3", "storage": "music2"}, {"title": "\u4f0a\u65af\u5766\u5821", "artist": ["\u5468\u6770\u4f26"], "file": "\u5468\u6770\u4f26 - \u4f0a\u65af\u5766\u5821.mp3", "storage": "music2"}, {"title": "\u4f60\u542c\u5f97\u5230", "artist": ["\u5468\u6770\u4f26"], "file": "\u5468\u6770\u4f26 - \u4f60\u542c\u5f97\u5230.mp3", "storage": "music2"}, {"title": "\u4f60\u597d\u5417", "artist": ["\u5468\u6770\u4f26"], "file": "\u5468\u6770\u4f26 - \u4f60\u597d\u5417.mp3", "storage": "music2"}, {"title": "\u4f60\u6bd4\u4ece\u524d\u5feb\u4e50", "artist": ["\u5468\u6770\u4f26"], "file": "\u5468\u6770\u4f26 - \u4f60\u6bd4\u4ece\u524d\u5feb\u4e50.mp3", "storage": "music2"}, {"title": "\u501f\u53e3", "artist": ["\u5468\u6770\u4f26"], "file": "\u5468\u6770\u4f26 - \u501f\u53e3.mp3", "storage": "music2"}, {"title": "\u514d\u8d39\u6559\u5b66\u5f55\u5f71\u5e26", "artist": ["\u5468\u6770\u4f26"], "file": "\u5468\u6770\u4f26 - \u514d\u8d39\u6559\u5b66\u5f55\u5f71\u5e26.mp3", "storage": "music2"}, {"title": "\u516c\u4e3b\u75c5", "artist": ["\u5468\u6770\u4f26"], "file": "\u5468\u6770\u4f26 - \u516c\u4e3b\u75c5.mp3", "storage": "music2"}, {"title": "\u516c\u516c\u504f\u5934\u75bc", "artist": ["\u5468\u6770\u4f26"], "file": "\u5468\u6770\u4f26 - \u516c\u516c\u504f\u5934\u75bc.mp3", "storage": "music2"}, {"title": "\u5170\u4ead\u5e8f", "artist": ["\u5468\u6770\u4f26"], "file": "\u5468\u6770\u4f26 - \u5170\u4ead\u5e8f.mp3", "storage": "music2"}, {"title": "\u5206\u88c2", "artist": ["\u5468\u6770\u4f26"], "file": "\u5468\u6770\u4f26 - \u5206\u88c2.mp3", "storage": "music2"}, {"title": "\u524d\u4e16\u60c5\u4eba", "artist": ["\u5468\u6770\u4f26"], "file": "\u5468\u6770\u4f26 - \u524d\u4e16\u60c5\u4eba.mp3", "storage": "music2"}, {"title": "\u5343\u91cc\u4e4b\u5916", "artist": ["\u5468\u6770\u4f26"], "file": "\u5468\u6770\u4f26 - \u5343\u91cc\u4e4b\u5916.mp3", "storage": "music2"}, {"title": "\u534a\u517d\u4eba", "artist": ["\u5468\u6770\u4f26"], "file": "\u5468\u6770\u4f26 - \u534a\u517d\u4eba.mp3", "storage": "music2"}, {"title": "\u534a\u5c9b\u94c1\u76d2", "artist": ["\u5468\u6770\u4f26"], "file": "\u5468\u6770\u4f26 - \u534a\u5c9b\u94c1\u76d2.mp3", "storage": "music2"}, {"title": "\u5370\u5730\u5b89\u8001\u6591\u9ce9", "artist": ["\u5468\u6770\u4f26"], "file": "\u5468\u6770\u4f26 - \u5370\u5730\u5b89\u8001\u6591\u9ce9.mp3", "storage": "music2"}, {"title": "\u53cc\u5200", "artist": ["\u5468\u6770\u4f26"], "file": "\u5468\u6770\u4f26 - \u53cc\u5200.mp3", "storage": "music2"}, {"title": "\u53cc\u622a\u68cd", "artist": ["\u5468\u6770\u4f26"], "file": "\u5468\u6770\u4f26 - \u53cc\u622a\u68cd.mp3", "storage": "music2"}, {"title": "\u53cd\u65b9\u5411\u7684\u949f", "artist": ["\u5468\u6770\u4f26"], "file": "\u5468\u6770\u4f26 - \u53cd\u65b9\u5411\u7684\u949f.mp3", "storage": "music2"}, {"title": "\u53d1\u5982\u96ea", "artist": ["\u5468\u6770\u4f26"], "file": "\u5468\u6770\u4f26 - \u53d1\u5982\u96ea.mp3", "storage": "music2"}, {"title": "\u53ef\u7231\u5973\u4eba", "artist": ["\u5468\u6770\u4f26"], "file": "\u5468\u6770\u4f26 - \u53ef\u7231\u5973\u4eba.mp3", "storage": "music2"}, {"title": "\u540c\u4e00\u79cd\u8c03\u8c03", "artist": ["\u5468\u6770\u4f26"], "file": "\u5468\u6770\u4f26 - \u540c\u4e00\u79cd\u8c03\u8c03.mp3", "storage": "music2"}, {"title": "\u542c\u5988\u5988\u7684\u8bdd", "artist": ["\u5468\u6770\u4f26"], "file": "\u5468\u6770\u4f26 - \u542c\u5988\u5988\u7684\u8bdd.mp3", "storage": "music2"}, {"title": "\u542c\u7238\u7238\u7684\u8bdd", "artist": ["\u5468\u6770\u4f26"], "file": "\u5468\u6770\u4f26 - \u542c\u7238\u7238\u7684\u8bdd.mp3", "storage": "music2"}, {"title": "\u542c\u89c1\u4e0b\u96e8\u7684\u58f0\u97f3", "artist": ["\u5468\u6770\u4f26"], "file": "\u5468\u6770\u4f26 - \u542c\u89c1\u4e0b\u96e8\u7684\u58f0\u97f3.mp3", "storage": "music2"}, {"title": "\u544a\u767d\u6c14\u7403", "artist": ["\u5468\u6770\u4f26"], "file": "\u5468\u6770\u4f26 - \u544a\u767d\u6c14\u7403.mp3", "storage": "music2"}, {"title": "\u54ea\u91cc\u90fd\u662f\u4f60", "artist": ["\u5468\u6770\u4f26"], "file": "\u5468\u6770\u4f26 - \u54ea\u91cc\u90fd\u662f\u4f60.mp3", "storage": "music2"}, {"title": "\u563b\u54c8\u7a7a\u59d0", "artist": ["\u5468\u6770\u4f26"], "file": "\u5468\u6770\u4f26 - \u563b\u54c8\u7a7a\u59d0.mp3", "storage": "music2"}, {"title": "\u56db\u5b63\u5217\u8f66", "artist": ["\u5468\u6770\u4f26"], "file": "\u5468\u6770\u4f26 - \u56db\u5b63\u5217\u8f66.mp3", "storage": "music2"}, {"title": "\u56db\u9762\u695a\u6b4c", "artist": ["\u5468\u6770\u4f26"], "file": "\u5468\u6770\u4f26 - \u56db\u9762\u695a\u6b4c.mp3", "storage": "music2"}, {"title": "\u56de\u5230\u8fc7\u53bb", "artist": ["\u5468\u6770\u4f26"], "file": "\u5468\u6770\u4f26 - \u56de\u5230\u8fc7\u53bb.mp3", "storage": "music2"}, {"title": "\u56ed\u6e38\u4f1a", "artist": ["\u5468\u6770\u4f26"], "file": "\u5468\u6770\u4f26 - \u56ed\u6e38\u4f1a.mp3", "storage": "music2"}, {"title": "\u56f0\u517d\u4e4b\u6597", "artist": ["\u5468\u6770\u4f26"], "file": "\u5468\u6770\u4f26 - \u56f0\u517d\u4e4b\u6597.mp3", "storage": "music2"}, {"title": "\u571f\u8033\u5176\u51b0\u6dc7\u6dcb", "artist": ["\u5468\u6770\u4f26"], "file": "\u5468\u6770\u4f26 - \u571f\u8033\u5176\u51b0\u6dc7\u6dcb.mp3", "storage": "music2"}, {"title": "\u5916\u5a46", "artist": ["\u5468\u6770\u4f26"], "file": "\u5468\u6770\u4f26 - \u5916\u5a46.mp3", "storage": "music2"}, {"title": "\u591c\u66f2", "artist": ["\u5468\u6770\u4f26"], "file": "\u5468\u6770\u4f26 - \u591c\u66f2.mp3", "storage": "music2"}, {"title": "\u591c\u7684\u7b2c\u4e03\u7ae0", "artist": ["\u5468\u6770\u4f26"], "file": "\u5468\u6770\u4f26 - \u591c\u7684\u7b2c\u4e03\u7ae0.mp3", "storage": "music2"}, {"title": "\u5927\u7b28\u949f", "artist": ["\u5468\u6770\u4f26"], "file": "\u5468\u6770\u4f26 - \u5927\u7b28\u949f.mp3", "storage": "music2"}, {"title": "\u5929\u6daf\u8fc7\u5ba2", "artist": ["\u5468\u6770\u4f26"], "file": "\u5468\u6770\u4f26 - \u5929\u6daf\u8fc7\u5ba2.mp3", "storage": "music2"}, {"title": "\u5979\u7684\u776b\u6bdb", "artist": ["\u5468\u6770\u4f26"], "file": "\u5468\u6770\u4f26 - \u5979\u7684\u776b\u6bdb.mp3", "storage": "music2"}, {"title": "\u597d\u4e45\u4e0d\u89c1", "artist": ["\u5468\u6770\u4f26"], "file": "\u5468\u6770\u4f26 - \u597d\u4e45\u4e0d\u89c1.mp3", "storage": "music2"}, {"title": "\u5a01\u5ec9\u53e4\u5821", "artist": ["\u5468\u6770\u4f26"], "file": "\u5468\u6770\u4f26 - \u5a01\u5ec9\u53e4\u5821.mp3", "storage": "music2"}, {"title": "\u5a18\u5b50", "artist": ["\u5468\u6770\u4f26"], "file": "\u5468\u6770\u4f26 - \u5a18\u5b50.mp3", "storage": "music2"}, {"title": "\u5b89\u9759", "artist": ["\u5468\u6770\u4f26"], "file": "\u5468\u6770\u4f26 - \u5b89\u9759.mp3", "storage": "music2"}, {"title": "\u5b8c\u7f8e\u4e3b\u4e49", "artist": ["\u5468\u6770\u4f26"], "file": "\u5468\u6770\u4f26 - \u5b8c\u7f8e\u4e3b\u4e49.mp3", "storage": "music2"}, {"title": "\u5bf9\u4e0d\u8d77", "artist": ["\u5468\u6770\u4f26"], "file": "\u5468\u6770\u4f26 - \u5bf9\u4e0d\u8d77.mp3", "storage": "music2"}, {"title": "\u5c06\u519b", "artist": ["\u5468\u6770\u4f26"], "file": "\u5468\u6770\u4f26 - \u5c06\u519b.mp3", "storage": "music2"}, {"title": "\u5e8a\u8fb9\u6545\u4e8b", "artist": ["\u5468\u6770\u4f26"], "file": "\u5468\u6770\u4f26 - \u5e8a\u8fb9\u6545\u4e8b.mp3", "storage": "music2"}, {"title": "\u5f00\u4e0d\u4e86\u53e3", "artist": ["\u5468\u6770\u4f26"], "file": "\u5468\u6770\u4f26 - \u5f00\u4e0d\u4e86\u53e3.mp3", "storage": "music2"}, {"title": "\u5fc3\u96e8", "artist": ["\u5468\u6770\u4f26"], "file": "\u5468\u6770\u4f26 - \u5fc3\u96e8.mp3", "storage": "music2"}, {"title": "\u5fcd\u8005", "artist": ["\u5468\u6770\u4f26"], "file": "\u5468\u6770\u4f26 - \u5fcd\u8005.mp3", "storage": "music2"}, {"title": "\u600e\u4e48\u4e86", "artist": ["\u5468\u6770\u4f26"], "file": "\u5468\u6770\u4f26 - \u600e\u4e48\u4e86.mp3", "storage": "music2"}, {"title": "\u60ca\u53f9\u53f7", "artist": ["\u5468\u6770\u4f26"], "file": "\u5468\u6770\u4f26 - \u60ca\u53f9\u53f7.mp3", "storage": "music2"}, {"title": "\u61e6\u592b", "artist": ["\u5468\u6770\u4f26"], "file": "\u5468\u6770\u4f26 - \u61e6\u592b.mp3", "storage": "music2"}, {"title": "\u6211\u7684\u5730\u76d8", "artist": ["\u5468\u6770\u4f26"], "file": "\u5468\u6770\u4f26 - \u6211\u7684\u5730\u76d8.mp3", "storage": "music2"}, {"title": "\u6211\u843d\u6cea\u00b7\u60c5\u7eea\u96f6\u788e", "artist": ["\u5468\u6770\u4f26"], "file": "\u5468\u6770\u4f26 - \u6211\u843d\u6cea\u00b7\u60c5\u7eea\u96f6\u788e.mp3", "storage": "music2"}, {"title": "\u6211\u8981\u590f\u5929", "artist": ["\u5468\u6770\u4f26"], "file": "\u5468\u6770\u4f26 - \u6211\u8981\u590f\u5929.mp3", "storage": "music2"}, {"title": "\u624b\u5199\u7684\u4ece\u524d", "artist": ["\u5468\u6770\u4f26"], "file": "\u5468\u6770\u4f26 - \u624b\u5199\u7684\u4ece\u524d.mp3", "storage": "music2"}, {"title": "\u624b\u8bed", "artist": ["\u5468\u6770\u4f26"], "file": "\u5468\u6770\u4f26 - \u624b\u8bed.mp3", "storage": "music2"}, {"title": "\u6401\u6d45", "artist": ["\u5468\u6770\u4f26"], "file": "\u5468\u6770\u4f26 - \u6401\u6d45.mp3", "storage": "music2"}, {"title": "\u6597\u725b", "artist": ["\u5468\u6770\u4f26"], "file": "\u5468\u6770\u4f26 - \u6597\u725b.mp3", "storage": "music2"}, {"title": "\u65f6\u5149\u673a", "artist": ["\u5468\u6770\u4f26"], "file": "\u5468\u6770\u4f26 - \u65f6\u5149\u673a.mp3", "storage": "music2"}, {"title": "\u660e\u660e\u5c31", "artist": ["\u5468\u6770\u4f26"], "file": "\u5468\u6770\u4f26 - \u660e\u660e\u5c31.mp3", "storage": "music2"}, {"title": "\u661f\u6674", "artist": ["\u5468\u6770\u4f26"], "file": "\u5468\u6770\u4f26 - \u661f\u6674.mp3", "storage": "music2"}, {"title": "\u6674\u5929", "artist": ["\u5468\u6770\u4f26"], "file": "\u5468\u6770\u4f26 - \u6674\u5929.mp3", "storage": "music2"}, {"title": "\u6697\u53f7", "artist": ["\u5468\u6770\u4f26"], "file": "\u5468\u6770\u4f26 - \u6697\u53f7.mp3", "storage": "music2"}, {"title": "\u6700\u540e\u7684\u6218\u5f79", "artist": ["\u5468\u6770\u4f26"], "file": "\u5468\u6770\u4f26 - \u6700\u540e\u7684\u6218\u5f79.mp3", "storage": "music2"}, {"title": "\u672c\u8349\u7eb2\u76ee", "artist": ["\u5468\u6770\u4f26"], "file": "\u5468\u6770\u4f26 - \u672c\u8349\u7eb2\u76ee.mp3", "storage": "music2"}, {"title": "\u67ab", "artist": ["\u5468\u6770\u4f26"], "file": "\u5468\u6770\u4f26 - \u67ab.mp3", "storage": "music2"}, {"title": "\u68a6\u60f3\u542f\u52a8", "artist": ["\u5468\u6770\u4f26"], "file": "\u5468\u6770\u4f26 - \u68a6\u60f3\u542f\u52a8.mp3", "storage": "music2"}, {"title": "\u68af\u7530", "artist": ["\u5468\u6770\u4f26"], "file": "\u5468\u6770\u4f26 - \u68af\u7530.mp3", "storage": "music2"}, {"title": "\u6b62\u6218\u4e4b\u6b87", "artist": ["\u5468\u6770\u4f26"], "file": "\u5468\u6770\u4f26 - \u6b62\u6218\u4e4b\u6b87.mp3", "storage": "music2"}, {"title": "\u6c34\u624b\u6015\u6c34", "artist": ["\u5468\u6770\u4f26"], "file": "\u5468\u6770\u4f26 - \u6c34\u624b\u6015\u6c34.mp3", "storage": "music2"}, {"title": "\u6d41\u6d6a\u8bd7\u4eba", "artist": ["\u5468\u6770\u4f26"], "file": "\u5468\u6770\u4f26 - \u6d41\u6d6a\u8bd7\u4eba.mp3", "storage": "music2"}, {"title": "\u6d6a\u6f2b\u624b\u673a", "artist": ["\u5468\u6770\u4f26"], "file": "\u5468\u6770\u4f26 - \u6d6a\u6f2b\u624b\u673a.mp3", "storage": "music2"}, {"title": "\u6f02\u79fb", "artist": ["\u5468\u6770\u4f26"], "file": "\u5468\u6770\u4f26 - \u6f02\u79fb.mp3", "storage": "music2"}, {"title": "\u706b\u8f66\u53e8\u4f4d\u53bb", "artist": ["\u5468\u6770\u4f26"], "file": "\u5468\u6770\u4f26 - \u706b\u8f66\u53e8\u4f4d\u53bb.mp3", "storage": "music2"}, {"title": "\u70df\u82b1\u6613\u51b7", "artist": ["\u5468\u6770\u4f26"], "file": "\u5468\u6770\u4f26 - \u70df\u82b1\u6613\u51b7.mp3", "storage": "music2"}, {"title": "\u7231\u4f60\u6ca1\u5dee", "artist": ["\u5468\u6770\u4f26"], "file": "\u5468\u6770\u4f26 - \u7231\u4f60\u6ca1\u5dee.mp3", "storage": "music2"}, {"title": "\u7231\u5728\u897f\u5143\u524d", "artist": ["\u5468\u6770\u4f26"], "file": "\u5468\u6770\u4f26 - \u7231\u5728\u897f\u5143\u524d.mp3", "storage": "music2"}, {"title": "\u7231\u60c5\u5e9f\u67f4", "artist": ["\u5468\u6770\u4f26"], "file": "\u5468\u6770\u4f26 - \u7231\u60c5\u5e9f\u67f4.mp3", "storage": "music2"}, {"title": "\u7231\u60c5\u60ac\u5d16", "artist": ["\u5468\u6770\u4f26"], "file": "\u5468\u6770\u4f26 - \u7231\u60c5\u60ac\u5d16.mp3", "storage": "music2"}, {"title": "\u7231\u7684\u98de\u884c\u65e5\u8bb0", "artist": ["\u5468\u6770\u4f26"], "file": "\u5468\u6770\u4f26 - \u7231\u7684\u98de\u884c\u65e5\u8bb0.mp3", "storage": "music2"}, {"title": "\u7237\u7237\u6ce1\u7684\u8336", "artist": ["\u5468\u6770\u4f26"], "file": "\u5468\u6770\u4f26 - \u7237\u7237\u6ce1\u7684\u8336.mp3", "storage": "music2"}, {"title": "\u7238\u6211\u56de\u6765\u4e86", "artist": ["\u5468\u6770\u4f26"], "file": "\u5468\u6770\u4f26 - \u7238\u6211\u56de\u6765\u4e86.mp3", "storage": "music2"}, {"title": "\u73ca\u745a\u6d77", "artist": ["\u5468\u6770\u4f26"], "file": "\u5468\u6770\u4f26 - \u73ca\u745a\u6d77.mp3", "storage": "music2"}, {"title": "\u7434\u4f24", "artist": ["\u5468\u6770\u4f26"], "file": "\u5468\u6770\u4f26 - \u7434\u4f24.mp3", "storage": "music2"}, {"title": "\u7597\u4f24\u70e7\u8089\u7cbd", "artist": ["\u5468\u6770\u4f26"], "file": "\u5468\u6770\u4f26 - \u7597\u4f24\u70e7\u8089\u7cbd.mp3", "storage": "music2"}, {"title": "\u767d\u8272\u98ce\u8f66", "artist": ["\u5468\u6770\u4f26"], "file": "\u5468\u6770\u4f26 - \u767d\u8272\u98ce\u8f66.mp3", "storage": "music2"}, {"title": "\u76ae\u5f71\u620f", "artist": ["\u5468\u6770\u4f26"], "file": "\u5468\u6770\u4f26 - \u76ae\u5f71\u620f.mp3", "storage": "music2"}, {"title": "\u7a3b\u9999", "artist": ["\u5468\u6770\u4f26"], "file": "\u5468\u6770\u4f26 - \u7a3b\u9999.mp3", "storage": "music2"}, {"title": "\u7a83\u7231", "artist": ["\u5468\u6770\u4f26"], "file": "\u5468\u6770\u4f26 - \u7a83\u7231.mp3", "storage": "music2"}, {"title": "\u7b80\u5355\u7231", "artist": ["\u5468\u6770\u4f26"], "file": "\u5468\u6770\u4f26 - \u7b80\u5355\u7231.mp3", "storage": "music2"}, {"title": "\u7b97\u4ec0\u4e48\u7537\u4eba", "artist": ["\u5468\u6770\u4f26"], "file": "\u5468\u6770\u4f26 - \u7b97\u4ec0\u4e48\u7537\u4eba.mp3", "storage": "music2"}, {"title": "\u7c73\u5170\u7684\u5c0f\u94c1\u5320", "artist": ["\u5468\u6770\u4f26"], "file": "\u5468\u6770\u4f26 - \u7c73\u5170\u7684\u5c0f\u94c1\u5320.mp3", "storage": "music2"}, {"title": "\u7ea2\u5c18\u5ba2\u6808", "artist": ["\u5468\u6770\u4f26"], "file": "\u5468\u6770\u4f26 - \u7ea2\u5c18\u5ba2\u6808.mp3", "storage": "music2"}, {"title": "\u7ea2\u78e8\u574a", "artist": ["\u5468\u6770\u4f26"], "file": "\u5468\u6770\u4f26 - \u7ea2\u78e8\u574a.mp3", "storage": "music2"}, {"title": "\u7ed9\u6211\u4e00\u9996\u6b4c\u7684\u65f6\u95f4", "artist": ["\u5468\u6770\u4f26"], "file": "\u5468\u6770\u4f26 - \u7ed9\u6211\u4e00\u9996\u6b4c\u7684\u65f6\u95f4.mp3", "storage": "music2"}, {"title": "\u7f8e\u4eba\u9c7c", "artist": ["\u5468\u6770\u4f26"], "file": "\u5468\u6770\u4f26 - \u7f8e\u4eba\u9c7c.mp3", "storage": "music2"}, {"title": "\u81ea\u5bfc\u81ea\u6f14", "artist": ["\u5468\u6770\u4f26"], "file": "\u5468\u6770\u4f26 - \u81ea\u5bfc\u81ea\u6f14.mp3", "storage": "music2"}, {"title": "\u82b1\u6d77", "artist": ["\u5468\u6770\u4f26"], "file": "\u5468\u6770\u4f26 - \u82b1\u6d77.mp3", "storage": "music2"}, {"title": "\u82f1\u96c4", "artist": ["\u5468\u6770\u4f26"], "file": "\u5468\u6770\u4f26 - \u82f1\u96c4.mp3", "storage": "music2"}, {"title": "\u83ca\u82b1\u53f0", "artist": ["\u5468\u6770\u4f26"], "file": "\u5468\u6770\u4f26 - \u83ca\u82b1\u53f0.mp3", "storage": "music2"}, {"title": "\u84dd\u8272\u98ce\u66b4", "artist": ["\u5468\u6770\u4f26"], "file": "\u5468\u6770\u4f26 - \u84dd\u8272\u98ce\u66b4.mp3", "storage": "music2"}, {"title": "\u86c7\u821e", "artist": ["\u5468\u6770\u4f26"], "file": "\u5468\u6770\u4f26 - \u86c7\u821e.mp3", "storage": "music2"}, {"title": "\u8717\u725b", "artist": ["\u5468\u6770\u4f26"], "file": "\u5468\u6770\u4f26 - \u8717\u725b.mp3", "storage": "music2"}, {"title": "\u8bf4\u4e86\u518d\u89c1", "artist": ["\u5468\u6770\u4f26"], "file": "\u5468\u6770\u4f26 - \u8bf4\u4e86\u518d\u89c1.mp3", "storage": "music2"}, {"title": "\u8bf4\u597d\u7684\u5e78\u798f\u5462", "artist": ["\u5468\u6770\u4f26"], "file": "\u5468\u6770\u4f26 - \u8bf4\u597d\u7684\u5e78\u798f\u5462.mp3", "storage": "music2"}, {"title": "\u8bf4\u8d70\u5c31\u8d70", "artist": ["\u5468\u6770\u4f26"], "file": "\u5468\u6770\u4f26 - \u8bf4\u8d70\u5c31\u8d70.mp3", "storage": "music2"}, {"title": "\u8d85\u4eba\u4e0d\u4f1a\u98de", "artist": ["\u5468\u6770\u4f26"], "file": "\u5468\u6770\u4f26 - \u8d85\u4eba\u4e0d\u4f1a\u98de.mp3", "storage": "music2"}, {"title": "\u8d85\u8dd1\u5973\u795e", "artist": ["\u5468\u6770\u4f26"], "file": "\u5468\u6770\u4f26 - \u8d85\u8dd1\u5973\u795e.mp3", "storage": "music2"}, {"title": "\u8de8\u65f6\u4ee3", "artist": ["\u5468\u6770\u4f26"], "file": "\u5468\u6770\u4f26 - \u8de8\u65f6\u4ee3.mp3", "storage": "music2"}, {"title": "\u8ff7\u8fed\u9999", "artist": ["\u5468\u6770\u4f26"], "file": "\u5468\u6770\u4f26 - \u8ff7\u8fed\u9999.mp3", "storage": "music2"}, {"title": "\u8ff7\u9b42\u66f2", "artist": ["\u5468\u6770\u4f26"], "file": "\u5468\u6770\u4f26 - \u8ff7\u9b42\u66f2.mp3", "storage": "music2"}, {"title": "\u9000\u540e", "artist": ["\u5468\u6770\u4f26"], "file": "\u5468\u6770\u4f26 - \u9000\u540e.mp3", "storage": "music2"}, {"title": "\u9006\u9cde", "artist": ["\u5468\u6770\u4f26"], "file": "\u5468\u6770\u4f26 - \u9006\u9cde.mp3", "storage": "music2"}, {"title": "\u9633\u660e\u5c71", "artist": ["\u5468\u6770\u4f26"], "file": "\u5468\u6770\u4f26 - \u9633\u660e\u5c71.mp3", "storage": "music2"}, {"title": "\u96e8\u4e0b\u4e00\u6574\u665a", "artist": ["\u5468\u6770\u4f26"], "file": "\u5468\u6770\u4f26 - \u96e8\u4e0b\u4e00\u6574\u665a.mp3", "storage": "music2"}, {"title": "\u978b\u5b50\u7279\u5927\u53f7", "artist": ["\u5468\u6770\u4f26"], "file": "\u5468\u6770\u4f26 - \u978b\u5b50\u7279\u5927\u53f7.mp3", "storage": "music2"}, {"title": "\u9b54\u672f\u5148\u751f", "artist": ["\u5468\u6770\u4f26"], "file": "\u5468\u6770\u4f26 - \u9b54\u672f\u5148\u751f.mp3", "storage": "music2"}, {"title": "\u9ea6\u82bd\u7cd6", "artist": ["\u5468\u6770\u4f26"], "file": "\u5468\u6770\u4f26 - \u9ea6\u82bd\u7cd6.mp3", "storage": "music2"}, {"title": "\u9ed1\u8272\u5e7d\u9ed8", "artist": ["\u5468\u6770\u4f26"], "file": "\u5468\u6770\u4f26 - \u9ed1\u8272\u5e7d\u9ed8.mp3", "storage": "music2"}, {"title": "\u9ed1\u8272\u6bdb\u8863", "artist": ["\u5468\u6770\u4f26"], "file": "\u5468\u6770\u4f26 - \u9ed1\u8272\u6bdb\u8863.mp3", "storage": "music2"}, {"title": "\u9f99\u5377\u98ce", "artist": ["\u5468\u6770\u4f26"], "file": "\u5468\u6770\u4f26 - \u9f99\u5377\u98ce.mp3", "storage": "music2"}, {"title": "\u9f99\u6218\u9a91\u58eb", "artist": ["\u5468\u6770\u4f26"], "file": "\u5468\u6770\u4f26 - \u9f99\u6218\u9a91\u58eb.mp3", "storage": "music2"}, {"title": "\u9f99\u62f3", "artist": ["\u5468\u6770\u4f26"], "file": "\u5468\u6770\u4f26 - \u9f99\u62f3.mp3", "storage": "music2"}, {"title": "\u4e0d\u8be5", "artist": ["\u5468\u6770\u4f26", "\u5f20\u60e0\u59b9"], "file": "\u5468\u6770\u4f26.\u5f20\u60e0\u59b9 - \u4e0d\u8be5.mp3", "storage": "music2"}, {"title": "\u6bd4\u8f83\u5927\u7684\u5927\u63d0\u7434", "artist": ["\u5468\u6770\u4f26", "\u6881\u5fc3\u9890", "\u6768\u745e\u4ee3"], "file": "\u5468\u6770\u4f26.\u6881\u5fc3\u9890.\u6768\u745e\u4ee3 - \u6bd4\u8f83\u5927\u7684\u5927\u63d0\u7434.mp3", "storage": "music2"}, {"title": "\u50bb\u7b11", "artist": ["\u5468\u6770\u4f26", "\u8881\u548f\u7433"], "file": "\u5468\u6770\u4f26.\u8881\u548f\u7433 - \u50bb\u7b11.mp3", "storage": "music2"}, {"title": "\u7231\u5982\u6f6e\u6c34", "artist": ["\u5f20\u4fe1\u54f2"], "file": "\u5f20\u4fe1\u54f2 - \u7231\u5982\u6f6e\u6c34.mp3", "storage": "music2"}, {"title": "\u8fc7\u706b", "artist": ["\u5f20\u4fe1\u54f2"], "file": "\u5f20\u4fe1\u54f2 - \u8fc7\u706b.mp3", "storage": "music2"}, {"title": "\u543b\u522b", "artist": ["\u5f20\u5b66\u53cb"], "file": "\u5f20\u5b66\u53cb - \u543b\u522b.mp3", "storage": "music2"}, {"title": "\u6211\u53ef\u4ee5\u62b1\u4f60\u5417", "artist": ["\u5f20\u60e0\u59b9"], "file": "\u5f20\u60e0\u59b9 - \u6211\u53ef\u4ee5\u62b1\u4f60\u5417.mp3", "storage": "music2"}, {"title": "\u8d81\u65e9", "artist": ["\u5f20\u60e0\u59b9"], "file": "\u5f20\u60e0\u59b9 - \u8d81\u65e9.mp3", "storage": "music2"}, {"title": "\u5e74\u8f6e", "artist": ["\u5f20\u78a7\u6668"], "file": "\u5f20\u78a7\u6668 - \u5e74\u8f6e.mp3", "storage": "music2"}, {"title": "\u518d\u89c1", "artist": ["\u5f20\u9707\u5cb3"], "file": "\u5f20\u9707\u5cb3 - \u518d\u89c1.mp3", "storage": "music2"}, {"title": "\u5dee\u4e0d\u591a\u5148\u751f", "artist": ["\u5f20\u9707\u5cb3"], "file": "\u5f20\u9707\u5cb3 - \u5dee\u4e0d\u591a\u5148\u751f.mp3", "storage": "music2"}, {"title": "\u7231\u6211\u522b\u8d70", "artist": ["\u5f20\u9707\u5cb3"], "file": "\u5f20\u9707\u5cb3 - \u7231\u6211\u522b\u8d70.mp3", "storage": "music2"}, {"title": "\u7231\u7684\u521d\u4f53\u9a8c", "artist": ["\u5f20\u9707\u5cb3"], "file": "\u5f20\u9707\u5cb3 - \u7231\u7684\u521d\u4f53\u9a8c.mp3", "storage": "music2"}, {"title": "\u753b\u5fc3", "artist": ["\u5f20\u9753\u9896"], "file": "\u5f20\u9753\u9896 - \u753b\u5fc3.mp3", "storage": "music2"}, {"title": "\u6b27\u82e5\u62c9", "artist": ["\u5f20\u97f6\u6db5"], "file": "\u5f20\u97f6\u6db5 - \u6b27\u82e5\u62c9.mp3", "storage": "music2"}, {"title": "\u9690\u5f62\u7684\u7fc5\u8180", "artist": ["\u5f20\u97f6\u6db5"], "file": "\u5f20\u97f6\u6db5 - \u9690\u5f62\u7684\u7fc5\u8180.mp3", "storage": "music2"}, {"title": "\u9752\u67e0", "artist": ["\u5f90\u79c9\u9f99"], "file": "\u5f90\u79c9\u9f99 - \u9752\u67e0.mp3", "storage": "music2"}, {"title": "\u5343\u5e74\u7f18", "artist": ["\u5fc3\u7136"], "file": "\u5fc3\u7136 - \u5343\u5e74\u7f18.mp3", "storage": "music2"}, {"title": "\u51c9\u51c9", "artist": ["\u6768\u5b97\u7eac\u3001\u5f20\u78a7\u6668"], "file": "\u6768\u5b97\u7eac\u3001\u5f20\u78a7\u6668 - \u51c9\u51c9.mp3", "storage": "music2"}, {"title": "\u53cc\u4eba\u884c", "artist": ["\u7199er"], "file": "\u7199er - \u53cc\u4eba\u884c.mp3", "storage": "music2"}, {"title": "\u590f\u65e5\u5faa\u73af", "artist": ["\u7199er"], "file": "\u7199er - \u590f\u65e5\u5faa\u73af.mp3", "storage": "music2"}, {"title": "\u7ffb\u82b1\u7ef3\u00a0", "artist": ["\u82d1\u820d"], "file": "\u82d1\u820d - \u7ffb\u82b1\u7ef3.mp3", "storage": "music2"}, {"title": "\u6e05\u98ce\u839e\u6708\u6d6e\u821f\u4ee4", "artist": ["\u8bb8\u591a\u8475"], "file": "\u8bb8\u591a\u8475 - \u6e05\u98ce\u839e\u6708\u6d6e\u821f\u4ee4.mp3", "storage": "music2"}, {"title": "\u7d20\u989c", "artist": ["\u8bb8\u5d69\u3001\u4f55\u66fc\u5a77"], "file": "\u8bb8\u5d69\u3001\u4f55\u66fc\u5a77 - \u7d20\u989c.mp3", "storage": "music2"}, {"title": "\u50cf\u98ce\u4e00\u6837\u81ea\u7531", "artist": ["\u8bb8\u5dcd"], "file": "\u8bb8\u5dcd - \u50cf\u98ce\u4e00\u6837\u81ea\u7531.mp3", "storage": "music2"}, {"title": "\u6267\u7740", "artist": ["\u8bb8\u5dcd"], "file": "\u8bb8\u5dcd - \u6267\u7740.mp3", "storage": "music2"}, {"title": "\u6545\u4e61", "artist": ["\u8bb8\u5dcd"], "file": "\u8bb8\u5dcd - \u6545\u4e61.mp3", "storage": "music2"}, {"title": "\u65c5\u884c", "artist": ["\u8bb8\u5dcd"], "file": "\u8bb8\u5dcd - \u65c5\u884c.mp3", "storage": "music2"}, {"title": "\u66fe\u7ecf\u7684\u4f60", "artist": ["\u8bb8\u5dcd"], "file": "\u8bb8\u5dcd - \u66fe\u7ecf\u7684\u4f60.mp3", "storage": "music2"}, {"title": "\u84dd\u83b2\u82b1", "artist": ["\u8bb8\u5dcd"], "file": "\u8bb8\u5dcd - \u84dd\u83b2\u82b1.mp3", "storage": "music2"}, {"title": "\u4e91\u957f", "artist": ["\u8d75\u94b6"], "file": "\u8d75\u94b6 - \u4e91\u957f.mp3", "storage": "music2"}, {"title": "\u5317\u4eac\u7684\u51ac\u5929", "artist": ["\u8d75\u96f7"], "file": "\u8d75\u96f7 - \u5317\u4eac\u7684\u51ac\u5929.mp3", "storage": "music2"}, {"title": "\u5357\u65b9\u59d1\u5a18", "artist": ["\u8d75\u96f7"], "file": "\u8d75\u96f7 - \u5357\u65b9\u59d1\u5a18.mp3", "storage": "music2"}, {"title": "\u5c0f\u5c4b", "artist": ["\u8d75\u96f7"], "file": "\u8d75\u96f7 - \u5c0f\u5c4b.mp3", "storage": "music2"}, {"title": "\u6210\u90fd", "artist": ["\u8d75\u96f7"], "file": "\u8d75\u96f7 - \u6210\u90fd.mp3", "storage": "music2"}, {"title": "\u6211\u4eec\u7684\u65f6\u5149", "artist": ["\u8d75\u96f7"], "file": "\u8d75\u96f7 - \u6211\u4eec\u7684\u65f6\u5149.mp3", "storage": "music2"}, {"title": "\u7406\u60f3", "artist": ["\u8d75\u96f7"], "file": "\u8d75\u96f7 - \u7406\u60f3.mp3", "storage": "music2"}, {"title": "\u753b", "artist": ["\u8d75\u96f7"], "file": "\u8d75\u96f7 - \u753b.mp3", "storage": "music2"}, {"title": "The Star", "artist": ["\u97f3\u9619\u8bd7\u542c"], "file": "\u97f3\u9619\u8bd7\u542c - The Star.mp3", "storage": "music2"}, {"title": "\u7ea2\u662d\u613f", "artist": ["\u97f3\u9619\u8bd7\u542c"], "file": "\u97f3\u9619\u8bd7\u542c - \u7ea2\u662d\u613f.mp3", "storage": "music2"}, {"title": "\u5341\u91cc\u70df\u6ce2", "artist": ["\u9e26\u9752"], "file": "\u9e26\u9752 - \u5341\u91cc\u70df\u6ce2.mp3", "storage": "music2"}, {"title": "\u5c71\u6c34\u5982\u8bd7", "artist": ["\u9e26\u9752"], "file": "\u9e26\u9752 - \u5c71\u6c34\u5982\u8bd7.mp3", "storage": "music2"}, {"title": "\u68a8\u82b1\u80e1\u540c", "artist": ["\u9e26\u9752"], "file": "\u9e26\u9752 - \u68a8\u82b1\u80e1\u540c.mp3", "storage": "music2"}]